{"page":551,"lines":[{"n":1,"type":"ayah","words":[{"t":"يَٰٓأَيُّهَا","k":"60:12","s":60,"e":0},{"t":"ٱلنَّبِيُّ","k":"60:12","s":60,"e":0},{"t":"إِذَا","k":"60:12","s":60,"e":0},{"t":"جَآءَكَ","k":"60:12","s":60,"e":0},{"t":"ٱلۡمُؤۡمِنَٰتُ","k":"60:12","s":60,"e":0},{"t":"يُبَايِعۡنَكَ","k":"60:12","s":60,"e":0},{"t":"عَلَىٰٓ","k":"60:12","s":60,"e":0},{"t":"أَن","k":"60:12","s":60,"e":0},{"t":"لَّا","k":"60:12","s":60,"e":0},{"t":"يُشۡرِكۡنَ","k":"60:12","s":60,"e":0}]},{"n":2,"type":"ayah","words":[{"t":"بِٱللَّهِ","k":"60:12","s":60,"e":0},{"t":"شَيۡـٔٗا","k":"60:12","s":60,"e":0},{"t":"وَلَا","k":"60:12","s":60,"e":0},{"t":"يَسۡرِقۡنَ","k":"60:12","s":60,"e":0},{"t":"وَلَا","k":"60:12","s":60,"e":0},{"t":"يَزۡنِينَ","k":"60:12","s":60,"e":0},{"t":"وَلَا","k":"60:12","s":60,"e":0},{"t":"يَقۡتُلۡنَ","k":"60:12","s":60,"e":0},{"t":"أَوۡلَٰدَهُنَّ","k":"60:12","s":60,"e":0},{"t":"وَلَا","k":"60:12","s":60,"e":0},{"t":"يَأۡتِينَ","k":"60:12","s":60,"e":0}]},{"n":3,"type":"ayah","words":[{"t":"بِبُهۡتَٰنٖ","k":"60:12","s":60,"e":0},{"t":"يَفۡتَرِينَهُۥ","k":"60:12","s":60,"e":0},{"t":"بَيۡنَ","k":"60:12","s":60,"e":0},{"t":"أَيۡدِيهِنَّ","k":"60:12","s":60,"e":0},{"t":"وَأَرۡجُلِهِنَّ","k":"60:12","s":60,"e":0},{"t":"وَلَا","k":"60:12","s":60,"e":0},{"t":"يَعۡصِينَكَ","k":"60:12","s":60,"e":0}]},{"n":4,"type":"ayah","words":[{"t":"فِي","k":"60:12","s":60,"e":0},{"t":"مَعۡرُوفٖ","k":"60:12","s":60,"e":0},{"t":"فَبَايِعۡهُنَّ","k":"60:12","s":60,"e":0},{"t":"وَٱسۡتَغۡفِرۡ","k":"60:12","s":60,"e":0},{"t":"لَهُنَّ","k":"60:12","s":60,"e":0},{"t":"ٱللَّهَۚ","k":"60:12","s":60,"e":0},{"t":"إِنَّ","k":"60:12","s":60,"e":0},{"t":"ٱللَّهَ","k":"60:12","s":60,"e":0},{"t":"غَفُورٞ","k":"60:12","s":60,"e":0},{"t":"رَّحِيمٞ","k":"60:12","s":60,"e":0}]},{"n":5,"type":"ayah","words":[{"t":"١٢","k":"60:12","s":60,"e":1},{"t":"يَٰٓأَيُّهَا","k":"60:13","s":60,"e":0},{"t":"ٱلَّذِينَ","k":"60:13","s":60,"e":0},{"t":"ءَامَنُواْ","k":"60:13","s":60,"e":0},{"t":"لَا","k":"60:13","s":60,"e":0},{"t":"تَتَوَلَّوۡاْ","k":"60:13","s":60,"e":0},{"t":"قَوۡمًا","k":"60:13","s":60,"e":0},{"t":"غَضِبَ","k":"60:13","s":60,"e":0},{"t":"ٱللَّهُ","k":"60:13","s":60,"e":0},{"t":"عَلَيۡهِمۡ","k":"60:13","s":60,"e":0}]},{"n":6,"type":"ayah","words":[{"t":"قَدۡ","k":"60:13","s":60,"e":0},{"t":"يَئِسُواْ","k":"60:13","s":60,"e":0},{"t":"مِنَ","k":"60:13","s":60,"e":0},{"t":"ٱلۡأٓخِرَةِ","k":"60:13","s":60,"e":0},{"t":"كَمَا","k":"60:13","s":60,"e":0},{"t":"يَئِسَ","k":"60:13","s":60,"e":0},{"t":"ٱلۡكُفَّارُ","k":"60:13","s":60,"e":0},{"t":"مِنۡ","k":"60:13","s":60,"e":0},{"t":"أَصۡحَٰبِ","k":"60:13","s":60,"e":0},{"t":"ٱلۡقُبُورِ","k":"60:13","s":60,"e":0},{"t":"١٣","k":"60:13","s":60,"e":1}],"c":1},{"n":7,"type":"surah","surah":61},{"n":8,"type":"basmala","surah":61},{"n":9,"type":"ayah","words":[{"t":"سَبَّحَ","k":"61:1","s":61,"e":0},{"t":"لِلَّهِ","k":"61:1","s":61,"e":0},{"t":"مَا","k":"61:1","s":61,"e":0},{"t":"فِي","k":"61:1","s":61,"e":0},{"t":"ٱلسَّمَٰوَٰتِ","k":"61:1","s":61,"e":0},{"t":"وَمَا","k":"61:1","s":61,"e":0},{"t":"فِي","k":"61:1","s":61,"e":0},{"t":"ٱلۡأَرۡضِۖ","k":"61:1","s":61,"e":0},{"t":"وَهُوَ","k":"61:1","s":61,"e":0},{"t":"ٱلۡعَزِيزُ","k":"61:1","s":61,"e":0},{"t":"ٱلۡحَكِيمُ","k":"61:1","s":61,"e":0}]},{"n":10,"type":"ayah","words":[{"t":"١","k":"61:1","s":61,"e":1},{"t":"يَٰٓأَيُّهَا","k":"61:2","s":61,"e":0},{"t":"ٱلَّذِينَ","k":"61:2","s":61,"e":0},{"t":"ءَامَنُواْ","k":"61:2","s":61,"e":0},{"t":"لِمَ","k":"61:2","s":61,"e":0},{"t":"تَقُولُونَ","k":"61:2","s":61,"e":0},{"t":"مَا","k":"61:2","s":61,"e":0},{"t":"لَا","k":"61:2","s":61,"e":0},{"t":"تَفۡعَلُونَ","k":"61:2","s":61,"e":0},{"t":"٢","k":"61:2","s":61,"e":1}]},{"n":11,"type":"ayah","words":[{"t":"كَبُرَ","k":"61:3","s":61,"e":0},{"t":"مَقۡتًا","k":"61:3","s":61,"e":0},{"t":"عِندَ","k":"61:3","s":61,"e":0},{"t":"ٱللَّهِ","k":"61:3","s":61,"e":0},{"t":"أَن","k":"61:3","s":61,"e":0},{"t":"تَقُولُواْ","k":"61:3","s":61,"e":0},{"t":"مَا","k":"61:3","s":61,"e":0},{"t":"لَا","k":"61:3","s":61,"e":0},{"t":"تَفۡعَلُونَ","k":"61:3","s":61,"e":0},{"t":"٣","k":"61:3","s":61,"e":1},{"t":"إِنَّ","k":"61:4","s":61,"e":0}]},{"n":12,"type":"ayah","words":[{"t":"ٱللَّهَ","k":"61:4","s":61,"e":0},{"t":"يُحِبُّ","k":"61:4","s":61,"e":0},{"t":"ٱلَّذِينَ","k":"61:4","s":61,"e":0},{"t":"يُقَٰتِلُونَ","k":"61:4","s":61,"e":0},{"t":"فِي","k":"61:4","s":61,"e":0},{"t":"سَبِيلِهِۦ","k":"61:4","s":61,"e":0},{"t":"صَفّٗا","k":"61:4","s":61,"e":0},{"t":"كَأَنَّهُم","k":"61:4","s":61,"e":0}]},{"n":13,"type":"ayah","words":[{"t":"بُنۡيَٰنٞ","k":"61:4","s":61,"e":0},{"t":"مَّرۡصُوصٞ","k":"61:4","s":61,"e":0},{"t":"٤","k":"61:4","s":61,"e":1},{"t":"وَإِذۡ","k":"61:5","s":61,"e":0},{"t":"قَالَ","k":"61:5","s":61,"e":0},{"t":"مُوسَىٰ","k":"61:5","s":61,"e":0},{"t":"لِقَوۡمِهِۦ","k":"61:5","s":61,"e":0},{"t":"يَٰقَوۡمِ","k":"61:5","s":61,"e":0},{"t":"لِمَ","k":"61:5","s":61,"e":0}]},{"n":14,"type":"ayah","words":[{"t":"تُؤۡذُونَنِي","k":"61:5","s":61,"e":0},{"t":"وَقَد","k":"61:5","s":61,"e":0},{"t":"تَّعۡلَمُونَ","k":"61:5","s":61,"e":0},{"t":"أَنِّي","k":"61:5","s":61,"e":0},{"t":"رَسُولُ","k":"61:5","s":61,"e":0},{"t":"ٱللَّهِ","k":"61:5","s":61,"e":0},{"t":"إِلَيۡكُمۡۖ","k":"61:5","s":61,"e":0},{"t":"فَلَمَّا","k":"61:5","s":61,"e":0}]},{"n":15,"type":"ayah","words":[{"t":"زَاغُوٓاْ","k":"61:5","s":61,"e":0},{"t":"أَزَاغَ","k":"61:5","s":61,"e":0},{"t":"ٱللَّهُ","k":"61:5","s":61,"e":0},{"t":"قُلُوبَهُمۡۚ","k":"61:5","s":61,"e":0},{"t":"وَٱللَّهُ","k":"61:5","s":61,"e":0},{"t":"لَا","k":"61:5","s":61,"e":0},{"t":"يَهۡدِي","k":"61:5","s":61,"e":0},{"t":"ٱلۡقَوۡمَ","k":"61:5","s":61,"e":0},{"t":"ٱلۡفَٰسِقِينَ","k":"61:5","s":61,"e":0},{"t":"٥","k":"61:5","s":61,"e":1}]}]}