{"page":468,"lines":[{"n":1,"type":"ayah","words":[{"t":"رَبَّنَا","k":"40:8","s":40,"e":0},{"t":"وَأَدۡخِلۡهُمۡ","k":"40:8","s":40,"e":0},{"t":"جَنَّٰتِ","k":"40:8","s":40,"e":0},{"t":"عَدۡنٍ","k":"40:8","s":40,"e":0},{"t":"ٱلَّتِي","k":"40:8","s":40,"e":0},{"t":"وَعَدتَّهُمۡ","k":"40:8","s":40,"e":0},{"t":"وَمَن","k":"40:8","s":40,"e":0},{"t":"صَلَحَ","k":"40:8","s":40,"e":0}]},{"n":2,"type":"ayah","words":[{"t":"مِنۡ","k":"40:8","s":40,"e":0},{"t":"ءَابَآئِهِمۡ","k":"40:8","s":40,"e":0},{"t":"وَأَزۡوَٰجِهِمۡ","k":"40:8","s":40,"e":0},{"t":"وَذُرِّيَّٰتِهِمۡۚ","k":"40:8","s":40,"e":0},{"t":"إِنَّكَ","k":"40:8","s":40,"e":0},{"t":"أَنتَ","k":"40:8","s":40,"e":0},{"t":"ٱلۡعَزِيزُ","k":"40:8","s":40,"e":0}]},{"n":3,"type":"ayah","words":[{"t":"ٱلۡحَكِيمُ","k":"40:8","s":40,"e":0},{"t":"٨","k":"40:8","s":40,"e":1},{"t":"وَقِهِمُ","k":"40:9","s":40,"e":0},{"t":"ٱلسَّيِّـَٔاتِۚ","k":"40:9","s":40,"e":0},{"t":"وَمَن","k":"40:9","s":40,"e":0},{"t":"تَقِ","k":"40:9","s":40,"e":0},{"t":"ٱلسَّيِّـَٔاتِ","k":"40:9","s":40,"e":0}]},{"n":4,"type":"ayah","words":[{"t":"يَوۡمَئِذٖ","k":"40:9","s":40,"e":0},{"t":"فَقَدۡ","k":"40:9","s":40,"e":0},{"t":"رَحِمۡتَهُۥۚ","k":"40:9","s":40,"e":0},{"t":"وَذَٰلِكَ","k":"40:9","s":40,"e":0},{"t":"هُوَ","k":"40:9","s":40,"e":0},{"t":"ٱلۡفَوۡزُ","k":"40:9","s":40,"e":0},{"t":"ٱلۡعَظِيمُ","k":"40:9","s":40,"e":0},{"t":"٩","k":"40:9","s":40,"e":1},{"t":"إِنَّ","k":"40:10","s":40,"e":0}]},{"n":5,"type":"ayah","words":[{"t":"ٱلَّذِينَ","k":"40:10","s":40,"e":0},{"t":"كَفَرُواْ","k":"40:10","s":40,"e":0},{"t":"يُنَادَوۡنَ","k":"40:10","s":40,"e":0},{"t":"لَمَقۡتُ","k":"40:10","s":40,"e":0},{"t":"ٱللَّهِ","k":"40:10","s":40,"e":0},{"t":"أَكۡبَرُ","k":"40:10","s":40,"e":0},{"t":"مِن","k":"40:10","s":40,"e":0},{"t":"مَّقۡتِكُمۡ","k":"40:10","s":40,"e":0}]},{"n":6,"type":"ayah","words":[{"t":"أَنفُسَكُمۡ","k":"40:10","s":40,"e":0},{"t":"إِذۡ","k":"40:10","s":40,"e":0},{"t":"تُدۡعَوۡنَ","k":"40:10","s":40,"e":0},{"t":"إِلَى","k":"40:10","s":40,"e":0},{"t":"ٱلۡإِيمَٰنِ","k":"40:10","s":40,"e":0},{"t":"فَتَكۡفُرُونَ","k":"40:10","s":40,"e":0},{"t":"١٠","k":"40:10","s":40,"e":1}]},{"n":7,"type":"ayah","words":[{"t":"قَالُواْ","k":"40:11","s":40,"e":0},{"t":"رَبَّنَآ","k":"40:11","s":40,"e":0},{"t":"أَمَتَّنَا","k":"40:11","s":40,"e":0},{"t":"ٱثۡنَتَيۡنِ","k":"40:11","s":40,"e":0},{"t":"وَأَحۡيَيۡتَنَا","k":"40:11","s":40,"e":0},{"t":"ٱثۡنَتَيۡنِ","k":"40:11","s":40,"e":0},{"t":"فَٱعۡتَرَفۡنَا","k":"40:11","s":40,"e":0},{"t":"بِذُنُوبِنَا","k":"40:11","s":40,"e":0}]},{"n":8,"type":"ayah","words":[{"t":"فَهَلۡ","k":"40:11","s":40,"e":0},{"t":"إِلَىٰ","k":"40:11","s":40,"e":0},{"t":"خُرُوجٖ","k":"40:11","s":40,"e":0},{"t":"مِّن","k":"40:11","s":40,"e":0},{"t":"سَبِيلٖ","k":"40:11","s":40,"e":0},{"t":"١١","k":"40:11","s":40,"e":1},{"t":"ذَٰلِكُم","k":"40:12","s":40,"e":0},{"t":"بِأَنَّهُۥٓ","k":"40:12","s":40,"e":0},{"t":"إِذَا","k":"40:12","s":40,"e":0},{"t":"دُعِيَ","k":"40:12","s":40,"e":0}]},{"n":9,"type":"ayah","words":[{"t":"ٱللَّهُ","k":"40:12","s":40,"e":0},{"t":"وَحۡدَهُۥ","k":"40:12","s":40,"e":0},{"t":"كَفَرۡتُمۡ","k":"40:12","s":40,"e":0},{"t":"وَإِن","k":"40:12","s":40,"e":0},{"t":"يُشۡرَكۡ","k":"40:12","s":40,"e":0},{"t":"بِهِۦ","k":"40:12","s":40,"e":0},{"t":"تُؤۡمِنُواْۚ","k":"40:12","s":40,"e":0},{"t":"فَٱلۡحُكۡمُ","k":"40:12","s":40,"e":0},{"t":"لِلَّهِ","k":"40:12","s":40,"e":0}]},{"n":10,"type":"ayah","words":[{"t":"ٱلۡعَلِيِّ","k":"40:12","s":40,"e":0},{"t":"ٱلۡكَبِيرِ","k":"40:12","s":40,"e":0},{"t":"١٢","k":"40:12","s":40,"e":1},{"t":"هُوَ","k":"40:13","s":40,"e":0},{"t":"ٱلَّذِي","k":"40:13","s":40,"e":0},{"t":"يُرِيكُمۡ","k":"40:13","s":40,"e":0},{"t":"ءَايَٰتِهِۦ","k":"40:13","s":40,"e":0},{"t":"وَيُنَزِّلُ","k":"40:13","s":40,"e":0}]},{"n":11,"type":"ayah","words":[{"t":"لَكُم","k":"40:13","s":40,"e":0},{"t":"مِّنَ","k":"40:13","s":40,"e":0},{"t":"ٱلسَّمَآءِ","k":"40:13","s":40,"e":0},{"t":"رِزۡقٗاۚ","k":"40:13","s":40,"e":0},{"t":"وَمَا","k":"40:13","s":40,"e":0},{"t":"يَتَذَكَّرُ","k":"40:13","s":40,"e":0},{"t":"إِلَّا","k":"40:13","s":40,"e":0},{"t":"مَن","k":"40:13","s":40,"e":0},{"t":"يُنِيبُ","k":"40:13","s":40,"e":0},{"t":"١٣","k":"40:13","s":40,"e":1}]},{"n":12,"type":"ayah","words":[{"t":"فَٱدۡعُواْ","k":"40:14","s":40,"e":0},{"t":"ٱللَّهَ","k":"40:14","s":40,"e":0},{"t":"مُخۡلِصِينَ","k":"40:14","s":40,"e":0},{"t":"لَهُ","k":"40:14","s":40,"e":0},{"t":"ٱلدِّينَ","k":"40:14","s":40,"e":0},{"t":"وَلَوۡ","k":"40:14","s":40,"e":0},{"t":"كَرِهَ","k":"40:14","s":40,"e":0},{"t":"ٱلۡكَٰفِرُونَ","k":"40:14","s":40,"e":0},{"t":"١٤","k":"40:14","s":40,"e":1}]},{"n":13,"type":"ayah","words":[{"t":"رَفِيعُ","k":"40:15","s":40,"e":0},{"t":"ٱلدَّرَجَٰتِ","k":"40:15","s":40,"e":0},{"t":"ذُو","k":"40:15","s":40,"e":0},{"t":"ٱلۡعَرۡشِ","k":"40:15","s":40,"e":0},{"t":"يُلۡقِي","k":"40:15","s":40,"e":0},{"t":"ٱلرُّوحَ","k":"40:15","s":40,"e":0},{"t":"مِنۡ","k":"40:15","s":40,"e":0},{"t":"أَمۡرِهِۦ","k":"40:15","s":40,"e":0},{"t":"عَلَىٰ","k":"40:15","s":40,"e":0},{"t":"مَن","k":"40:15","s":40,"e":0}]},{"n":14,"type":"ayah","words":[{"t":"يَشَآءُ","k":"40:15","s":40,"e":0},{"t":"مِنۡ","k":"40:15","s":40,"e":0},{"t":"عِبَادِهِۦ","k":"40:15","s":40,"e":0},{"t":"لِيُنذِرَ","k":"40:15","s":40,"e":0},{"t":"يَوۡمَ","k":"40:15","s":40,"e":0},{"t":"ٱلتَّلَاقِ","k":"40:15","s":40,"e":0},{"t":"١٥","k":"40:15","s":40,"e":1},{"t":"يَوۡمَ","k":"40:16","s":40,"e":0},{"t":"هُم","k":"40:16","s":40,"e":0},{"t":"بَٰرِزُونَۖ","k":"40:16","s":40,"e":0},{"t":"لَا","k":"40:16","s":40,"e":0},{"t":"يَخۡفَىٰ","k":"40:16","s":40,"e":0}]},{"n":15,"type":"ayah","words":[{"t":"عَلَى","k":"40:16","s":40,"e":0},{"t":"ٱللَّهِ","k":"40:16","s":40,"e":0},{"t":"مِنۡهُمۡ","k":"40:16","s":40,"e":0},{"t":"شَيۡءٞۚ","k":"40:16","s":40,"e":0},{"t":"لِّمَنِ","k":"40:16","s":40,"e":0},{"t":"ٱلۡمُلۡكُ","k":"40:16","s":40,"e":0},{"t":"ٱلۡيَوۡمَۖ","k":"40:16","s":40,"e":0},{"t":"لِلَّهِ","k":"40:16","s":40,"e":0},{"t":"ٱلۡوَٰحِدِ","k":"40:16","s":40,"e":0},{"t":"ٱلۡقَهَّارِ","k":"40:16","s":40,"e":0},{"t":"١٦","k":"40:16","s":40,"e":1}]}]}