{"page":221,"lines":[{"n":1,"type":"ayah","words":[{"t":"وَإِن","k":"10:107","s":10,"e":0},{"t":"يَمۡسَسۡكَ","k":"10:107","s":10,"e":0},{"t":"ٱللَّهُ","k":"10:107","s":10,"e":0},{"t":"بِضُرّٖ","k":"10:107","s":10,"e":0},{"t":"فَلَا","k":"10:107","s":10,"e":0},{"t":"كَاشِفَ","k":"10:107","s":10,"e":0},{"t":"لَهُۥٓ","k":"10:107","s":10,"e":0},{"t":"إِلَّا","k":"10:107","s":10,"e":0},{"t":"هُوَۖ","k":"10:107","s":10,"e":0},{"t":"وَإِن","k":"10:107","s":10,"e":0}]},{"n":2,"type":"ayah","words":[{"t":"يُرِدۡكَ","k":"10:107","s":10,"e":0},{"t":"بِخَيۡرٖ","k":"10:107","s":10,"e":0},{"t":"فَلَا","k":"10:107","s":10,"e":0},{"t":"رَآدَّ","k":"10:107","s":10,"e":0},{"t":"لِفَضۡلِهِۦۚ","k":"10:107","s":10,"e":0},{"t":"يُصِيبُ","k":"10:107","s":10,"e":0},{"t":"بِهِۦ","k":"10:107","s":10,"e":0},{"t":"مَن","k":"10:107","s":10,"e":0},{"t":"يَشَآءُ","k":"10:107","s":10,"e":0},{"t":"مِنۡ","k":"10:107","s":10,"e":0},{"t":"عِبَادِهِۦۚ","k":"10:107","s":10,"e":0}]},{"n":3,"type":"ayah","words":[{"t":"وَهُوَ","k":"10:107","s":10,"e":0},{"t":"ٱلۡغَفُورُ","k":"10:107","s":10,"e":0},{"t":"ٱلرَّحِيمُ","k":"10:107","s":10,"e":0},{"t":"١٠٧","k":"10:107","s":10,"e":1},{"t":"قُلۡ","k":"10:108","s":10,"e":0},{"t":"يَٰٓأَيُّهَا","k":"10:108","s":10,"e":0},{"t":"ٱلنَّاسُ","k":"10:108","s":10,"e":0},{"t":"قَدۡ","k":"10:108","s":10,"e":0},{"t":"جَآءَكُمُ","k":"10:108","s":10,"e":0}]},{"n":4,"type":"ayah","words":[{"t":"ٱلۡحَقُّ","k":"10:108","s":10,"e":0},{"t":"مِن","k":"10:108","s":10,"e":0},{"t":"رَّبِّكُمۡۖ","k":"10:108","s":10,"e":0},{"t":"فَمَنِ","k":"10:108","s":10,"e":0},{"t":"ٱهۡتَدَىٰ","k":"10:108","s":10,"e":0},{"t":"فَإِنَّمَا","k":"10:108","s":10,"e":0},{"t":"يَهۡتَدِي","k":"10:108","s":10,"e":0},{"t":"لِنَفۡسِهِۦۖ","k":"10:108","s":10,"e":0},{"t":"وَمَن","k":"10:108","s":10,"e":0}]},{"n":5,"type":"ayah","words":[{"t":"ضَلَّ","k":"10:108","s":10,"e":0},{"t":"فَإِنَّمَا","k":"10:108","s":10,"e":0},{"t":"يَضِلُّ","k":"10:108","s":10,"e":0},{"t":"عَلَيۡهَاۖ","k":"10:108","s":10,"e":0},{"t":"وَمَآ","k":"10:108","s":10,"e":0},{"t":"أَنَا۠","k":"10:108","s":10,"e":0},{"t":"عَلَيۡكُم","k":"10:108","s":10,"e":0},{"t":"بِوَكِيلٖ","k":"10:108","s":10,"e":0},{"t":"١٠٨","k":"10:108","s":10,"e":1},{"t":"وَٱتَّبِعۡ","k":"10:109","s":10,"e":0}]},{"n":6,"type":"ayah","words":[{"t":"مَا","k":"10:109","s":10,"e":0},{"t":"يُوحَىٰٓ","k":"10:109","s":10,"e":0},{"t":"إِلَيۡكَ","k":"10:109","s":10,"e":0},{"t":"وَٱصۡبِرۡ","k":"10:109","s":10,"e":0},{"t":"حَتَّىٰ","k":"10:109","s":10,"e":0},{"t":"يَحۡكُمَ","k":"10:109","s":10,"e":0},{"t":"ٱللَّهُۚ","k":"10:109","s":10,"e":0},{"t":"وَهُوَ","k":"10:109","s":10,"e":0},{"t":"خَيۡرُ","k":"10:109","s":10,"e":0},{"t":"ٱلۡحَٰكِمِينَ","k":"10:109","s":10,"e":0},{"t":"١٠٩","k":"10:109","s":10,"e":1}],"c":1},{"n":7,"type":"surah","surah":11},{"n":8,"type":"basmala","surah":11},{"n":9,"type":"ayah","words":[{"t":"الٓرۚ","k":"11:1","s":11,"e":0},{"t":"كِتَٰبٌ","k":"11:1","s":11,"e":0},{"t":"أُحۡكِمَتۡ","k":"11:1","s":11,"e":0},{"t":"ءَايَٰتُهُۥ","k":"11:1","s":11,"e":0},{"t":"ثُمَّ","k":"11:1","s":11,"e":0},{"t":"فُصِّلَتۡ","k":"11:1","s":11,"e":0},{"t":"مِن","k":"11:1","s":11,"e":0},{"t":"لَّدُنۡ","k":"11:1","s":11,"e":0},{"t":"حَكِيمٍ","k":"11:1","s":11,"e":0},{"t":"خَبِيرٍ","k":"11:1","s":11,"e":0},{"t":"١","k":"11:1","s":11,"e":1}]},{"n":10,"type":"ayah","words":[{"t":"أَلَّا","k":"11:2","s":11,"e":0},{"t":"تَعۡبُدُوٓاْ","k":"11:2","s":11,"e":0},{"t":"إِلَّا","k":"11:2","s":11,"e":0},{"t":"ٱللَّهَۚ","k":"11:2","s":11,"e":0},{"t":"إِنَّنِي","k":"11:2","s":11,"e":0},{"t":"لَكُم","k":"11:2","s":11,"e":0},{"t":"مِّنۡهُ","k":"11:2","s":11,"e":0},{"t":"نَذِيرٞ","k":"11:2","s":11,"e":0},{"t":"وَبَشِيرٞ","k":"11:2","s":11,"e":0},{"t":"٢","k":"11:2","s":11,"e":1},{"t":"وَأَنِ","k":"11:3","s":11,"e":0},{"t":"ٱسۡتَغۡفِرُواْ","k":"11:3","s":11,"e":0}]},{"n":11,"type":"ayah","words":[{"t":"رَبَّكُمۡ","k":"11:3","s":11,"e":0},{"t":"ثُمَّ","k":"11:3","s":11,"e":0},{"t":"تُوبُوٓاْ","k":"11:3","s":11,"e":0},{"t":"إِلَيۡهِ","k":"11:3","s":11,"e":0},{"t":"يُمَتِّعۡكُم","k":"11:3","s":11,"e":0},{"t":"مَّتَٰعًا","k":"11:3","s":11,"e":0},{"t":"حَسَنًا","k":"11:3","s":11,"e":0},{"t":"إِلَىٰٓ","k":"11:3","s":11,"e":0},{"t":"أَجَلٖ","k":"11:3","s":11,"e":0},{"t":"مُّسَمّٗى","k":"11:3","s":11,"e":0},{"t":"وَيُؤۡتِ","k":"11:3","s":11,"e":0}]},{"n":12,"type":"ayah","words":[{"t":"كُلَّ","k":"11:3","s":11,"e":0},{"t":"ذِي","k":"11:3","s":11,"e":0},{"t":"فَضۡلٖ","k":"11:3","s":11,"e":0},{"t":"فَضۡلَهُۥۖ","k":"11:3","s":11,"e":0},{"t":"وَإِن","k":"11:3","s":11,"e":0},{"t":"تَوَلَّوۡاْ","k":"11:3","s":11,"e":0},{"t":"فَإِنِّيٓ","k":"11:3","s":11,"e":0},{"t":"أَخَافُ","k":"11:3","s":11,"e":0},{"t":"عَلَيۡكُمۡ","k":"11:3","s":11,"e":0},{"t":"عَذَابَ","k":"11:3","s":11,"e":0},{"t":"يَوۡمٖ","k":"11:3","s":11,"e":0}]},{"n":13,"type":"ayah","words":[{"t":"كَبِيرٍ","k":"11:3","s":11,"e":0},{"t":"٣","k":"11:3","s":11,"e":1},{"t":"إِلَى","k":"11:4","s":11,"e":0},{"t":"ٱللَّهِ","k":"11:4","s":11,"e":0},{"t":"مَرۡجِعُكُمۡۖ","k":"11:4","s":11,"e":0},{"t":"وَهُوَ","k":"11:4","s":11,"e":0},{"t":"عَلَىٰ","k":"11:4","s":11,"e":0},{"t":"كُلِّ","k":"11:4","s":11,"e":0},{"t":"شَيۡءٖ","k":"11:4","s":11,"e":0},{"t":"قَدِيرٌ","k":"11:4","s":11,"e":0},{"t":"٤","k":"11:4","s":11,"e":1},{"t":"أَلَآ","k":"11:5","s":11,"e":0},{"t":"إِنَّهُمۡ","k":"11:5","s":11,"e":0}]},{"n":14,"type":"ayah","words":[{"t":"يَثۡنُونَ","k":"11:5","s":11,"e":0},{"t":"صُدُورَهُمۡ","k":"11:5","s":11,"e":0},{"t":"لِيَسۡتَخۡفُواْ","k":"11:5","s":11,"e":0},{"t":"مِنۡهُۚ","k":"11:5","s":11,"e":0},{"t":"أَلَا","k":"11:5","s":11,"e":0},{"t":"حِينَ","k":"11:5","s":11,"e":0},{"t":"يَسۡتَغۡشُونَ","k":"11:5","s":11,"e":0},{"t":"ثِيَابَهُمۡ","k":"11:5","s":11,"e":0}]},{"n":15,"type":"ayah","words":[{"t":"يَعۡلَمُ","k":"11:5","s":11,"e":0},{"t":"مَا","k":"11:5","s":11,"e":0},{"t":"يُسِرُّونَ","k":"11:5","s":11,"e":0},{"t":"وَمَا","k":"11:5","s":11,"e":0},{"t":"يُعۡلِنُونَۚ","k":"11:5","s":11,"e":0},{"t":"إِنَّهُۥ","k":"11:5","s":11,"e":0},{"t":"عَلِيمُۢ","k":"11:5","s":11,"e":0},{"t":"بِذَاتِ","k":"11:5","s":11,"e":0},{"t":"ٱلصُّدُورِ","k":"11:5","s":11,"e":0},{"t":"٥","k":"11:5","s":11,"e":1}]}]}