{"page":14,"lines":[{"n":1,"type":"ayah","words":[{"t":"وَلَمَّا","k":"2:89","s":2,"e":0},{"t":"جَآءَهُمۡ","k":"2:89","s":2,"e":0},{"t":"كِتَٰبٞ","k":"2:89","s":2,"e":0},{"t":"مِّنۡ","k":"2:89","s":2,"e":0},{"t":"عِندِ","k":"2:89","s":2,"e":0},{"t":"ٱللَّهِ","k":"2:89","s":2,"e":0},{"t":"مُصَدِّقٞ","k":"2:89","s":2,"e":0},{"t":"لِّمَا","k":"2:89","s":2,"e":0},{"t":"مَعَهُمۡ","k":"2:89","s":2,"e":0},{"t":"وَكَانُواْ","k":"2:89","s":2,"e":0}]},{"n":2,"type":"ayah","words":[{"t":"مِن","k":"2:89","s":2,"e":0},{"t":"قَبۡلُ","k":"2:89","s":2,"e":0},{"t":"يَسۡتَفۡتِحُونَ","k":"2:89","s":2,"e":0},{"t":"عَلَى","k":"2:89","s":2,"e":0},{"t":"ٱلَّذِينَ","k":"2:89","s":2,"e":0},{"t":"كَفَرُواْ","k":"2:89","s":2,"e":0},{"t":"فَلَمَّا","k":"2:89","s":2,"e":0},{"t":"جَآءَهُم","k":"2:89","s":2,"e":0}]},{"n":3,"type":"ayah","words":[{"t":"مَّا","k":"2:89","s":2,"e":0},{"t":"عَرَفُواْ","k":"2:89","s":2,"e":0},{"t":"كَفَرُواْ","k":"2:89","s":2,"e":0},{"t":"بِهِۦۚ","k":"2:89","s":2,"e":0},{"t":"فَلَعۡنَةُ","k":"2:89","s":2,"e":0},{"t":"ٱللَّهِ","k":"2:89","s":2,"e":0},{"t":"عَلَى","k":"2:89","s":2,"e":0},{"t":"ٱلۡكَٰفِرِينَ","k":"2:89","s":2,"e":0},{"t":"٨٩","k":"2:89","s":2,"e":1}]},{"n":4,"type":"ayah","words":[{"t":"بِئۡسَمَا","k":"2:90","s":2,"e":0},{"t":"ٱشۡتَرَوۡاْ","k":"2:90","s":2,"e":0},{"t":"بِهِۦٓ","k":"2:90","s":2,"e":0},{"t":"أَنفُسَهُمۡ","k":"2:90","s":2,"e":0},{"t":"أَن","k":"2:90","s":2,"e":0},{"t":"يَكۡفُرُواْ","k":"2:90","s":2,"e":0},{"t":"بِمَآ","k":"2:90","s":2,"e":0},{"t":"أَنزَلَ","k":"2:90","s":2,"e":0}]},{"n":5,"type":"ayah","words":[{"t":"ٱللَّهُ","k":"2:90","s":2,"e":0},{"t":"بَغۡيًا","k":"2:90","s":2,"e":0},{"t":"أَن","k":"2:90","s":2,"e":0},{"t":"يُنَزِّلَ","k":"2:90","s":2,"e":0},{"t":"ٱللَّهُ","k":"2:90","s":2,"e":0},{"t":"مِن","k":"2:90","s":2,"e":0},{"t":"فَضۡلِهِۦ","k":"2:90","s":2,"e":0},{"t":"عَلَىٰ","k":"2:90","s":2,"e":0},{"t":"مَن","k":"2:90","s":2,"e":0},{"t":"يَشَآءُ","k":"2:90","s":2,"e":0},{"t":"مِنۡ","k":"2:90","s":2,"e":0},{"t":"عِبَادِهِۦۖ","k":"2:90","s":2,"e":0}]},{"n":6,"type":"ayah","words":[{"t":"فَبَآءُو","k":"2:90","s":2,"e":0},{"t":"بِغَضَبٍ","k":"2:90","s":2,"e":0},{"t":"عَلَىٰ","k":"2:90","s":2,"e":0},{"t":"غَضَبٖۚ","k":"2:90","s":2,"e":0},{"t":"وَلِلۡكَٰفِرِينَ","k":"2:90","s":2,"e":0},{"t":"عَذَابٞ","k":"2:90","s":2,"e":0},{"t":"مُّهِينٞ","k":"2:90","s":2,"e":0}]},{"n":7,"type":"ayah","words":[{"t":"٩٠","k":"2:90","s":2,"e":1},{"t":"وَإِذَا","k":"2:91","s":2,"e":0},{"t":"قِيلَ","k":"2:91","s":2,"e":0},{"t":"لَهُمۡ","k":"2:91","s":2,"e":0},{"t":"ءَامِنُواْ","k":"2:91","s":2,"e":0},{"t":"بِمَآ","k":"2:91","s":2,"e":0},{"t":"أَنزَلَ","k":"2:91","s":2,"e":0},{"t":"ٱللَّهُ","k":"2:91","s":2,"e":0},{"t":"قَالُواْ","k":"2:91","s":2,"e":0},{"t":"نُؤۡمِنُ","k":"2:91","s":2,"e":0},{"t":"بِمَآ","k":"2:91","s":2,"e":0}]},{"n":8,"type":"ayah","words":[{"t":"أُنزِلَ","k":"2:91","s":2,"e":0},{"t":"عَلَيۡنَا","k":"2:91","s":2,"e":0},{"t":"وَيَكۡفُرُونَ","k":"2:91","s":2,"e":0},{"t":"بِمَا","k":"2:91","s":2,"e":0},{"t":"وَرَآءَهُۥ","k":"2:91","s":2,"e":0},{"t":"وَهُوَ","k":"2:91","s":2,"e":0},{"t":"ٱلۡحَقُّ","k":"2:91","s":2,"e":0},{"t":"مُصَدِّقٗا","k":"2:91","s":2,"e":0}]},{"n":9,"type":"ayah","words":[{"t":"لِّمَا","k":"2:91","s":2,"e":0},{"t":"مَعَهُمۡۗ","k":"2:91","s":2,"e":0},{"t":"قُلۡ","k":"2:91","s":2,"e":0},{"t":"فَلِمَ","k":"2:91","s":2,"e":0},{"t":"تَقۡتُلُونَ","k":"2:91","s":2,"e":0},{"t":"أَنۢبِيَآءَ","k":"2:91","s":2,"e":0},{"t":"ٱللَّهِ","k":"2:91","s":2,"e":0},{"t":"مِن","k":"2:91","s":2,"e":0},{"t":"قَبۡلُ","k":"2:91","s":2,"e":0},{"t":"إِن","k":"2:91","s":2,"e":0},{"t":"كُنتُم","k":"2:91","s":2,"e":0}]},{"n":10,"type":"ayah","words":[{"t":"مُّؤۡمِنِينَ","k":"2:91","s":2,"e":0},{"t":"٩١","k":"2:91","s":2,"e":1},{"t":"۞ وَلَقَدۡ","k":"2:92","s":2,"e":0},{"t":"جَآءَكُم","k":"2:92","s":2,"e":0},{"t":"مُّوسَىٰ","k":"2:92","s":2,"e":0},{"t":"بِٱلۡبَيِّنَٰتِ","k":"2:92","s":2,"e":0}]},{"n":11,"type":"ayah","words":[{"t":"ثُمَّ","k":"2:92","s":2,"e":0},{"t":"ٱتَّخَذۡتُمُ","k":"2:92","s":2,"e":0},{"t":"ٱلۡعِجۡلَ","k":"2:92","s":2,"e":0},{"t":"مِنۢ","k":"2:92","s":2,"e":0},{"t":"بَعۡدِهِۦ","k":"2:92","s":2,"e":0},{"t":"وَأَنتُمۡ","k":"2:92","s":2,"e":0},{"t":"ظَٰلِمُونَ","k":"2:92","s":2,"e":0},{"t":"٩٢","k":"2:92","s":2,"e":1}]},{"n":12,"type":"ayah","words":[{"t":"وَإِذۡ","k":"2:93","s":2,"e":0},{"t":"أَخَذۡنَا","k":"2:93","s":2,"e":0},{"t":"مِيثَٰقَكُمۡ","k":"2:93","s":2,"e":0},{"t":"وَرَفَعۡنَا","k":"2:93","s":2,"e":0},{"t":"فَوۡقَكُمُ","k":"2:93","s":2,"e":0},{"t":"ٱلطُّورَ","k":"2:93","s":2,"e":0},{"t":"خُذُواْ","k":"2:93","s":2,"e":0}]},{"n":13,"type":"ayah","words":[{"t":"مَآ","k":"2:93","s":2,"e":0},{"t":"ءَاتَيۡنَٰكُم","k":"2:93","s":2,"e":0},{"t":"بِقُوَّةٖ","k":"2:93","s":2,"e":0},{"t":"وَٱسۡمَعُواْۖ","k":"2:93","s":2,"e":0},{"t":"قَالُواْ","k":"2:93","s":2,"e":0},{"t":"سَمِعۡنَا","k":"2:93","s":2,"e":0},{"t":"وَعَصَيۡنَا","k":"2:93","s":2,"e":0}]},{"n":14,"type":"ayah","words":[{"t":"وَأُشۡرِبُواْ","k":"2:93","s":2,"e":0},{"t":"فِي","k":"2:93","s":2,"e":0},{"t":"قُلُوبِهِمُ","k":"2:93","s":2,"e":0},{"t":"ٱلۡعِجۡلَ","k":"2:93","s":2,"e":0},{"t":"بِكُفۡرِهِمۡۚ","k":"2:93","s":2,"e":0},{"t":"قُلۡ","k":"2:93","s":2,"e":0}]},{"n":15,"type":"ayah","words":[{"t":"بِئۡسَمَا","k":"2:93","s":2,"e":0},{"t":"يَأۡمُرُكُم","k":"2:93","s":2,"e":0},{"t":"بِهِۦٓ","k":"2:93","s":2,"e":0},{"t":"إِيمَٰنُكُمۡ","k":"2:93","s":2,"e":0},{"t":"إِن","k":"2:93","s":2,"e":0},{"t":"كُنتُم","k":"2:93","s":2,"e":0},{"t":"مُّؤۡمِنِينَ","k":"2:93","s":2,"e":0},{"t":"٩٣","k":"2:93","s":2,"e":1}]}]}