{"page":415,"lines":[{"n":1,"type":"basmala","surah":32},{"n":2,"type":"ayah","words":[{"t":"الٓمٓ","k":"32:1","s":32,"e":0},{"t":"١","k":"32:1","s":32,"e":1},{"t":"تَنزِيلُ","k":"32:2","s":32,"e":0},{"t":"ٱلۡكِتَٰبِ","k":"32:2","s":32,"e":0},{"t":"لَا","k":"32:2","s":32,"e":0},{"t":"رَيۡبَ","k":"32:2","s":32,"e":0},{"t":"فِيهِ","k":"32:2","s":32,"e":0},{"t":"مِن","k":"32:2","s":32,"e":0},{"t":"رَّبِّ","k":"32:2","s":32,"e":0},{"t":"ٱلۡعَٰلَمِينَ","k":"32:2","s":32,"e":0}]},{"n":3,"type":"ayah","words":[{"t":"٢","k":"32:2","s":32,"e":1},{"t":"أَمۡ","k":"32:3","s":32,"e":0},{"t":"يَقُولُونَ","k":"32:3","s":32,"e":0},{"t":"ٱفۡتَرَىٰهُۚ","k":"32:3","s":32,"e":0},{"t":"بَلۡ","k":"32:3","s":32,"e":0},{"t":"هُوَ","k":"32:3","s":32,"e":0},{"t":"ٱلۡحَقُّ","k":"32:3","s":32,"e":0},{"t":"مِن","k":"32:3","s":32,"e":0},{"t":"رَّبِّكَ","k":"32:3","s":32,"e":0},{"t":"لِتُنذِرَ","k":"32:3","s":32,"e":0},{"t":"قَوۡمٗا","k":"32:3","s":32,"e":0}]},{"n":4,"type":"ayah","words":[{"t":"مَّآ","k":"32:3","s":32,"e":0},{"t":"أَتَىٰهُم","k":"32:3","s":32,"e":0},{"t":"مِّن","k":"32:3","s":32,"e":0},{"t":"نَّذِيرٖ","k":"32:3","s":32,"e":0},{"t":"مِّن","k":"32:3","s":32,"e":0},{"t":"قَبۡلِكَ","k":"32:3","s":32,"e":0},{"t":"لَعَلَّهُمۡ","k":"32:3","s":32,"e":0},{"t":"يَهۡتَدُونَ","k":"32:3","s":32,"e":0},{"t":"٣","k":"32:3","s":32,"e":1},{"t":"ٱللَّهُ","k":"32:4","s":32,"e":0}]},{"n":5,"type":"ayah","words":[{"t":"ٱلَّذِي","k":"32:4","s":32,"e":0},{"t":"خَلَقَ","k":"32:4","s":32,"e":0},{"t":"ٱلسَّمَٰوَٰتِ","k":"32:4","s":32,"e":0},{"t":"وَٱلۡأَرۡضَ","k":"32:4","s":32,"e":0},{"t":"وَمَا","k":"32:4","s":32,"e":0},{"t":"بَيۡنَهُمَا","k":"32:4","s":32,"e":0},{"t":"فِي","k":"32:4","s":32,"e":0},{"t":"سِتَّةِ","k":"32:4","s":32,"e":0},{"t":"أَيَّامٖ","k":"32:4","s":32,"e":0}]},{"n":6,"type":"ayah","words":[{"t":"ثُمَّ","k":"32:4","s":32,"e":0},{"t":"ٱسۡتَوَىٰ","k":"32:4","s":32,"e":0},{"t":"عَلَى","k":"32:4","s":32,"e":0},{"t":"ٱلۡعَرۡشِۖ","k":"32:4","s":32,"e":0},{"t":"مَا","k":"32:4","s":32,"e":0},{"t":"لَكُم","k":"32:4","s":32,"e":0},{"t":"مِّن","k":"32:4","s":32,"e":0},{"t":"دُونِهِۦ","k":"32:4","s":32,"e":0},{"t":"مِن","k":"32:4","s":32,"e":0},{"t":"وَلِيّٖ","k":"32:4","s":32,"e":0},{"t":"وَلَا","k":"32:4","s":32,"e":0},{"t":"شَفِيعٍۚ","k":"32:4","s":32,"e":0},{"t":"أَفَلَا","k":"32:4","s":32,"e":0}]},{"n":7,"type":"ayah","words":[{"t":"تَتَذَكَّرُونَ","k":"32:4","s":32,"e":0},{"t":"٤","k":"32:4","s":32,"e":1},{"t":"يُدَبِّرُ","k":"32:5","s":32,"e":0},{"t":"ٱلۡأَمۡرَ","k":"32:5","s":32,"e":0},{"t":"مِنَ","k":"32:5","s":32,"e":0},{"t":"ٱلسَّمَآءِ","k":"32:5","s":32,"e":0},{"t":"إِلَى","k":"32:5","s":32,"e":0},{"t":"ٱلۡأَرۡضِ","k":"32:5","s":32,"e":0},{"t":"ثُمَّ","k":"32:5","s":32,"e":0},{"t":"يَعۡرُجُ","k":"32:5","s":32,"e":0}]},{"n":8,"type":"ayah","words":[{"t":"إِلَيۡهِ","k":"32:5","s":32,"e":0},{"t":"فِي","k":"32:5","s":32,"e":0},{"t":"يَوۡمٖ","k":"32:5","s":32,"e":0},{"t":"كَانَ","k":"32:5","s":32,"e":0},{"t":"مِقۡدَارُهُۥٓ","k":"32:5","s":32,"e":0},{"t":"أَلۡفَ","k":"32:5","s":32,"e":0},{"t":"سَنَةٖ","k":"32:5","s":32,"e":0},{"t":"مِّمَّا","k":"32:5","s":32,"e":0},{"t":"تَعُدُّونَ","k":"32:5","s":32,"e":0},{"t":"٥","k":"32:5","s":32,"e":1},{"t":"ذَٰلِكَ","k":"32:6","s":32,"e":0}]},{"n":9,"type":"ayah","words":[{"t":"عَٰلِمُ","k":"32:6","s":32,"e":0},{"t":"ٱلۡغَيۡبِ","k":"32:6","s":32,"e":0},{"t":"وَٱلشَّهَٰدَةِ","k":"32:6","s":32,"e":0},{"t":"ٱلۡعَزِيزُ","k":"32:6","s":32,"e":0},{"t":"ٱلرَّحِيمُ","k":"32:6","s":32,"e":0},{"t":"٦","k":"32:6","s":32,"e":1},{"t":"ٱلَّذِيٓ","k":"32:7","s":32,"e":0},{"t":"أَحۡسَنَ","k":"32:7","s":32,"e":0}]},{"n":10,"type":"ayah","words":[{"t":"كُلَّ","k":"32:7","s":32,"e":0},{"t":"شَيۡءٍ","k":"32:7","s":32,"e":0},{"t":"خَلَقَهُۥۖ","k":"32:7","s":32,"e":0},{"t":"وَبَدَأَ","k":"32:7","s":32,"e":0},{"t":"خَلۡقَ","k":"32:7","s":32,"e":0},{"t":"ٱلۡإِنسَٰنِ","k":"32:7","s":32,"e":0},{"t":"مِن","k":"32:7","s":32,"e":0},{"t":"طِينٖ","k":"32:7","s":32,"e":0},{"t":"٧","k":"32:7","s":32,"e":1},{"t":"ثُمَّ","k":"32:8","s":32,"e":0},{"t":"جَعَلَ","k":"32:8","s":32,"e":0}]},{"n":11,"type":"ayah","words":[{"t":"نَسۡلَهُۥ","k":"32:8","s":32,"e":0},{"t":"مِن","k":"32:8","s":32,"e":0},{"t":"سُلَٰلَةٖ","k":"32:8","s":32,"e":0},{"t":"مِّن","k":"32:8","s":32,"e":0},{"t":"مَّآءٖ","k":"32:8","s":32,"e":0},{"t":"مَّهِينٖ","k":"32:8","s":32,"e":0},{"t":"٨","k":"32:8","s":32,"e":1},{"t":"ثُمَّ","k":"32:9","s":32,"e":0},{"t":"سَوَّىٰهُ","k":"32:9","s":32,"e":0},{"t":"وَنَفَخَ","k":"32:9","s":32,"e":0},{"t":"فِيهِ","k":"32:9","s":32,"e":0}]},{"n":12,"type":"ayah","words":[{"t":"مِن","k":"32:9","s":32,"e":0},{"t":"رُّوحِهِۦۖ","k":"32:9","s":32,"e":0},{"t":"وَجَعَلَ","k":"32:9","s":32,"e":0},{"t":"لَكُمُ","k":"32:9","s":32,"e":0},{"t":"ٱلسَّمۡعَ","k":"32:9","s":32,"e":0},{"t":"وَٱلۡأَبۡصَٰرَ","k":"32:9","s":32,"e":0},{"t":"وَٱلۡأَفۡـِٔدَةَۚ","k":"32:9","s":32,"e":0},{"t":"قَلِيلٗا","k":"32:9","s":32,"e":0}]},{"n":13,"type":"ayah","words":[{"t":"مَّا","k":"32:9","s":32,"e":0},{"t":"تَشۡكُرُونَ","k":"32:9","s":32,"e":0},{"t":"٩","k":"32:9","s":32,"e":1},{"t":"وَقَالُوٓاْ","k":"32:10","s":32,"e":0},{"t":"أَءِذَا","k":"32:10","s":32,"e":0},{"t":"ضَلَلۡنَا","k":"32:10","s":32,"e":0},{"t":"فِي","k":"32:10","s":32,"e":0},{"t":"ٱلۡأَرۡضِ","k":"32:10","s":32,"e":0},{"t":"أَءِنَّا","k":"32:10","s":32,"e":0},{"t":"لَفِي","k":"32:10","s":32,"e":0}]},{"n":14,"type":"ayah","words":[{"t":"خَلۡقٖ","k":"32:10","s":32,"e":0},{"t":"جَدِيدِۭۚ","k":"32:10","s":32,"e":0},{"t":"بَلۡ","k":"32:10","s":32,"e":0},{"t":"هُم","k":"32:10","s":32,"e":0},{"t":"بِلِقَآءِ","k":"32:10","s":32,"e":0},{"t":"رَبِّهِمۡ","k":"32:10","s":32,"e":0},{"t":"كَٰفِرُونَ","k":"32:10","s":32,"e":0},{"t":"١٠","k":"32:10","s":32,"e":1},{"t":"۞ قُلۡ","k":"32:11","s":32,"e":0},{"t":"يَتَوَفَّىٰكُم","k":"32:11","s":32,"e":0}]},{"n":15,"type":"ayah","words":[{"t":"مَّلَكُ","k":"32:11","s":32,"e":0},{"t":"ٱلۡمَوۡتِ","k":"32:11","s":32,"e":0},{"t":"ٱلَّذِي","k":"32:11","s":32,"e":0},{"t":"وُكِّلَ","k":"32:11","s":32,"e":0},{"t":"بِكُمۡ","k":"32:11","s":32,"e":0},{"t":"ثُمَّ","k":"32:11","s":32,"e":0},{"t":"إِلَىٰ","k":"32:11","s":32,"e":0},{"t":"رَبِّكُمۡ","k":"32:11","s":32,"e":0},{"t":"تُرۡجَعُونَ","k":"32:11","s":32,"e":0},{"t":"١١","k":"32:11","s":32,"e":1}]}]}