{"page":530,"lines":[{"n":1,"type":"ayah","words":[{"t":"وَنَبِّئۡهُمۡ","k":"54:28","s":54,"e":0},{"t":"أَنَّ","k":"54:28","s":54,"e":0},{"t":"ٱلۡمَآءَ","k":"54:28","s":54,"e":0},{"t":"قِسۡمَةُۢ","k":"54:28","s":54,"e":0},{"t":"بَيۡنَهُمۡۖ","k":"54:28","s":54,"e":0},{"t":"كُلُّ","k":"54:28","s":54,"e":0},{"t":"شِرۡبٖ","k":"54:28","s":54,"e":0},{"t":"مُّحۡتَضَرٞ","k":"54:28","s":54,"e":0},{"t":"٢٨","k":"54:28","s":54,"e":1},{"t":"فَنَادَوۡاْ","k":"54:29","s":54,"e":0},{"t":"صَاحِبَهُمۡ","k":"54:29","s":54,"e":0}]},{"n":2,"type":"ayah","words":[{"t":"فَتَعَاطَىٰ","k":"54:29","s":54,"e":0},{"t":"فَعَقَرَ","k":"54:29","s":54,"e":0},{"t":"٢٩","k":"54:29","s":54,"e":1},{"t":"فَكَيۡفَ","k":"54:30","s":54,"e":0},{"t":"كَانَ","k":"54:30","s":54,"e":0},{"t":"عَذَابِي","k":"54:30","s":54,"e":0},{"t":"وَنُذُرِ","k":"54:30","s":54,"e":0},{"t":"٣٠","k":"54:30","s":54,"e":1},{"t":"إِنَّآ","k":"54:31","s":54,"e":0},{"t":"أَرۡسَلۡنَا","k":"54:31","s":54,"e":0},{"t":"عَلَيۡهِمۡ","k":"54:31","s":54,"e":0}]},{"n":3,"type":"ayah","words":[{"t":"صَيۡحَةٗ","k":"54:31","s":54,"e":0},{"t":"وَٰحِدَةٗ","k":"54:31","s":54,"e":0},{"t":"فَكَانُواْ","k":"54:31","s":54,"e":0},{"t":"كَهَشِيمِ","k":"54:31","s":54,"e":0},{"t":"ٱلۡمُحۡتَظِرِ","k":"54:31","s":54,"e":0},{"t":"٣١","k":"54:31","s":54,"e":1},{"t":"وَلَقَدۡ","k":"54:32","s":54,"e":0},{"t":"يَسَّرۡنَا","k":"54:32","s":54,"e":0},{"t":"ٱلۡقُرۡءَانَ","k":"54:32","s":54,"e":0}]},{"n":4,"type":"ayah","words":[{"t":"لِلذِّكۡرِ","k":"54:32","s":54,"e":0},{"t":"فَهَلۡ","k":"54:32","s":54,"e":0},{"t":"مِن","k":"54:32","s":54,"e":0},{"t":"مُّدَّكِرٖ","k":"54:32","s":54,"e":0},{"t":"٣٢","k":"54:32","s":54,"e":1},{"t":"كَذَّبَتۡ","k":"54:33","s":54,"e":0},{"t":"قَوۡمُ","k":"54:33","s":54,"e":0},{"t":"لُوطِۭ","k":"54:33","s":54,"e":0},{"t":"بِٱلنُّذُرِ","k":"54:33","s":54,"e":0},{"t":"٣٣","k":"54:33","s":54,"e":1},{"t":"إِنَّآ","k":"54:34","s":54,"e":0},{"t":"أَرۡسَلۡنَا","k":"54:34","s":54,"e":0}]},{"n":5,"type":"ayah","words":[{"t":"عَلَيۡهِمۡ","k":"54:34","s":54,"e":0},{"t":"حَاصِبًا","k":"54:34","s":54,"e":0},{"t":"إِلَّآ","k":"54:34","s":54,"e":0},{"t":"ءَالَ","k":"54:34","s":54,"e":0},{"t":"لُوطٖۖ","k":"54:34","s":54,"e":0},{"t":"نَّجَّيۡنَٰهُم","k":"54:34","s":54,"e":0},{"t":"بِسَحَرٖ","k":"54:34","s":54,"e":0},{"t":"٣٤","k":"54:34","s":54,"e":1},{"t":"نِّعۡمَةٗ","k":"54:35","s":54,"e":0},{"t":"مِّنۡ","k":"54:35","s":54,"e":0},{"t":"عِندِنَاۚ","k":"54:35","s":54,"e":0}]},{"n":6,"type":"ayah","words":[{"t":"كَذَٰلِكَ","k":"54:35","s":54,"e":0},{"t":"نَجۡزِي","k":"54:35","s":54,"e":0},{"t":"مَن","k":"54:35","s":54,"e":0},{"t":"شَكَرَ","k":"54:35","s":54,"e":0},{"t":"٣٥","k":"54:35","s":54,"e":1},{"t":"وَلَقَدۡ","k":"54:36","s":54,"e":0},{"t":"أَنذَرَهُم","k":"54:36","s":54,"e":0},{"t":"بَطۡشَتَنَا","k":"54:36","s":54,"e":0},{"t":"فَتَمَارَوۡاْ","k":"54:36","s":54,"e":0}]},{"n":7,"type":"ayah","words":[{"t":"بِٱلنُّذُرِ","k":"54:36","s":54,"e":0},{"t":"٣٦","k":"54:36","s":54,"e":1},{"t":"وَلَقَدۡ","k":"54:37","s":54,"e":0},{"t":"رَٰوَدُوهُ","k":"54:37","s":54,"e":0},{"t":"عَن","k":"54:37","s":54,"e":0},{"t":"ضَيۡفِهِۦ","k":"54:37","s":54,"e":0},{"t":"فَطَمَسۡنَآ","k":"54:37","s":54,"e":0},{"t":"أَعۡيُنَهُمۡ","k":"54:37","s":54,"e":0},{"t":"فَذُوقُواْ","k":"54:37","s":54,"e":0}]},{"n":8,"type":"ayah","words":[{"t":"عَذَابِي","k":"54:37","s":54,"e":0},{"t":"وَنُذُرِ","k":"54:37","s":54,"e":0},{"t":"٣٧","k":"54:37","s":54,"e":1},{"t":"وَلَقَدۡ","k":"54:38","s":54,"e":0},{"t":"صَبَّحَهُم","k":"54:38","s":54,"e":0},{"t":"بُكۡرَةً","k":"54:38","s":54,"e":0},{"t":"عَذَابٞ","k":"54:38","s":54,"e":0},{"t":"مُّسۡتَقِرّٞ","k":"54:38","s":54,"e":0},{"t":"٣٨","k":"54:38","s":54,"e":1}]},{"n":9,"type":"ayah","words":[{"t":"فَذُوقُواْ","k":"54:39","s":54,"e":0},{"t":"عَذَابِي","k":"54:39","s":54,"e":0},{"t":"وَنُذُرِ","k":"54:39","s":54,"e":0},{"t":"٣٩","k":"54:39","s":54,"e":1},{"t":"وَلَقَدۡ","k":"54:40","s":54,"e":0},{"t":"يَسَّرۡنَا","k":"54:40","s":54,"e":0},{"t":"ٱلۡقُرۡءَانَ","k":"54:40","s":54,"e":0},{"t":"لِلذِّكۡرِ","k":"54:40","s":54,"e":0},{"t":"فَهَلۡ","k":"54:40","s":54,"e":0},{"t":"مِن","k":"54:40","s":54,"e":0},{"t":"مُّدَّكِرٖ","k":"54:40","s":54,"e":0}]},{"n":10,"type":"ayah","words":[{"t":"٤٠","k":"54:40","s":54,"e":1},{"t":"وَلَقَدۡ","k":"54:41","s":54,"e":0},{"t":"جَآءَ","k":"54:41","s":54,"e":0},{"t":"ءَالَ","k":"54:41","s":54,"e":0},{"t":"فِرۡعَوۡنَ","k":"54:41","s":54,"e":0},{"t":"ٱلنُّذُرُ","k":"54:41","s":54,"e":0},{"t":"٤١","k":"54:41","s":54,"e":1},{"t":"كَذَّبُواْ","k":"54:42","s":54,"e":0},{"t":"بِـَٔايَٰتِنَا","k":"54:42","s":54,"e":0},{"t":"كُلِّهَا","k":"54:42","s":54,"e":0},{"t":"فَأَخَذۡنَٰهُمۡ","k":"54:42","s":54,"e":0}]},{"n":11,"type":"ayah","words":[{"t":"أَخۡذَ","k":"54:42","s":54,"e":0},{"t":"عَزِيزٖ","k":"54:42","s":54,"e":0},{"t":"مُّقۡتَدِرٍ","k":"54:42","s":54,"e":0},{"t":"٤٢","k":"54:42","s":54,"e":1},{"t":"أَكُفَّارُكُمۡ","k":"54:43","s":54,"e":0},{"t":"خَيۡرٞ","k":"54:43","s":54,"e":0},{"t":"مِّنۡ","k":"54:43","s":54,"e":0},{"t":"أُوْلَٰٓئِكُمۡ","k":"54:43","s":54,"e":0},{"t":"أَمۡ","k":"54:43","s":54,"e":0},{"t":"لَكُم","k":"54:43","s":54,"e":0},{"t":"بَرَآءَةٞ","k":"54:43","s":54,"e":0}]},{"n":12,"type":"ayah","words":[{"t":"فِي","k":"54:43","s":54,"e":0},{"t":"ٱلزُّبُرِ","k":"54:43","s":54,"e":0},{"t":"٤٣","k":"54:43","s":54,"e":1},{"t":"أَمۡ","k":"54:44","s":54,"e":0},{"t":"يَقُولُونَ","k":"54:44","s":54,"e":0},{"t":"نَحۡنُ","k":"54:44","s":54,"e":0},{"t":"جَمِيعٞ","k":"54:44","s":54,"e":0},{"t":"مُّنتَصِرٞ","k":"54:44","s":54,"e":0},{"t":"٤٤","k":"54:44","s":54,"e":1},{"t":"سَيُهۡزَمُ","k":"54:45","s":54,"e":0},{"t":"ٱلۡجَمۡعُ","k":"54:45","s":54,"e":0}]},{"n":13,"type":"ayah","words":[{"t":"وَيُوَلُّونَ","k":"54:45","s":54,"e":0},{"t":"ٱلدُّبُرَ","k":"54:45","s":54,"e":0},{"t":"٤٥","k":"54:45","s":54,"e":1},{"t":"بَلِ","k":"54:46","s":54,"e":0},{"t":"ٱلسَّاعَةُ","k":"54:46","s":54,"e":0},{"t":"مَوۡعِدُهُمۡ","k":"54:46","s":54,"e":0},{"t":"وَٱلسَّاعَةُ","k":"54:46","s":54,"e":0},{"t":"أَدۡهَىٰ","k":"54:46","s":54,"e":0},{"t":"وَأَمَرُّ","k":"54:46","s":54,"e":0}]},{"n":14,"type":"ayah","words":[{"t":"٤٦","k":"54:46","s":54,"e":1},{"t":"إِنَّ","k":"54:47","s":54,"e":0},{"t":"ٱلۡمُجۡرِمِينَ","k":"54:47","s":54,"e":0},{"t":"فِي","k":"54:47","s":54,"e":0},{"t":"ضَلَٰلٖ","k":"54:47","s":54,"e":0},{"t":"وَسُعُرٖ","k":"54:47","s":54,"e":0},{"t":"٤٧","k":"54:47","s":54,"e":1},{"t":"يَوۡمَ","k":"54:48","s":54,"e":0},{"t":"يُسۡحَبُونَ","k":"54:48","s":54,"e":0},{"t":"فِي","k":"54:48","s":54,"e":0},{"t":"ٱلنَّارِ","k":"54:48","s":54,"e":0}]},{"n":15,"type":"ayah","words":[{"t":"عَلَىٰ","k":"54:48","s":54,"e":0},{"t":"وُجُوهِهِمۡ","k":"54:48","s":54,"e":0},{"t":"ذُوقُواْ","k":"54:48","s":54,"e":0},{"t":"مَسَّ","k":"54:48","s":54,"e":0},{"t":"سَقَرَ","k":"54:48","s":54,"e":0},{"t":"٤٨","k":"54:48","s":54,"e":1},{"t":"إِنَّا","k":"54:49","s":54,"e":0},{"t":"كُلَّ","k":"54:49","s":54,"e":0},{"t":"شَيۡءٍ","k":"54:49","s":54,"e":0},{"t":"خَلَقۡنَٰهُ","k":"54:49","s":54,"e":0},{"t":"بِقَدَرٖ","k":"54:49","s":54,"e":0},{"t":"٤٩","k":"54:49","s":54,"e":1}]}]}