{"page":369,"lines":[{"n":1,"type":"ayah","words":[{"t":"لَعَلَّنَا","k":"26:40","s":26,"e":0},{"t":"نَتَّبِعُ","k":"26:40","s":26,"e":0},{"t":"ٱلسَّحَرَةَ","k":"26:40","s":26,"e":0},{"t":"إِن","k":"26:40","s":26,"e":0},{"t":"كَانُواْ","k":"26:40","s":26,"e":0},{"t":"هُمُ","k":"26:40","s":26,"e":0},{"t":"ٱلۡغَٰلِبِينَ","k":"26:40","s":26,"e":0},{"t":"٤٠","k":"26:40","s":26,"e":1},{"t":"فَلَمَّا","k":"26:41","s":26,"e":0},{"t":"جَآءَ","k":"26:41","s":26,"e":0},{"t":"ٱلسَّحَرَةُ","k":"26:41","s":26,"e":0}]},{"n":2,"type":"ayah","words":[{"t":"قَالُواْ","k":"26:41","s":26,"e":0},{"t":"لِفِرۡعَوۡنَ","k":"26:41","s":26,"e":0},{"t":"أَئِنَّ","k":"26:41","s":26,"e":0},{"t":"لَنَا","k":"26:41","s":26,"e":0},{"t":"لَأَجۡرًا","k":"26:41","s":26,"e":0},{"t":"إِن","k":"26:41","s":26,"e":0},{"t":"كُنَّا","k":"26:41","s":26,"e":0},{"t":"نَحۡنُ","k":"26:41","s":26,"e":0},{"t":"ٱلۡغَٰلِبِينَ","k":"26:41","s":26,"e":0},{"t":"٤١","k":"26:41","s":26,"e":1},{"t":"قَالَ","k":"26:42","s":26,"e":0},{"t":"نَعَمۡ","k":"26:42","s":26,"e":0}]},{"n":3,"type":"ayah","words":[{"t":"وَإِنَّكُمۡ","k":"26:42","s":26,"e":0},{"t":"إِذٗا","k":"26:42","s":26,"e":0},{"t":"لَّمِنَ","k":"26:42","s":26,"e":0},{"t":"ٱلۡمُقَرَّبِينَ","k":"26:42","s":26,"e":0},{"t":"٤٢","k":"26:42","s":26,"e":1},{"t":"قَالَ","k":"26:43","s":26,"e":0},{"t":"لَهُم","k":"26:43","s":26,"e":0},{"t":"مُّوسَىٰٓ","k":"26:43","s":26,"e":0},{"t":"أَلۡقُواْ","k":"26:43","s":26,"e":0},{"t":"مَآ","k":"26:43","s":26,"e":0},{"t":"أَنتُم","k":"26:43","s":26,"e":0},{"t":"مُّلۡقُونَ","k":"26:43","s":26,"e":0}]},{"n":4,"type":"ayah","words":[{"t":"٤٣","k":"26:43","s":26,"e":1},{"t":"فَأَلۡقَوۡاْ","k":"26:44","s":26,"e":0},{"t":"حِبَالَهُمۡ","k":"26:44","s":26,"e":0},{"t":"وَعِصِيَّهُمۡ","k":"26:44","s":26,"e":0},{"t":"وَقَالُواْ","k":"26:44","s":26,"e":0},{"t":"بِعِزَّةِ","k":"26:44","s":26,"e":0},{"t":"فِرۡعَوۡنَ","k":"26:44","s":26,"e":0},{"t":"إِنَّا","k":"26:44","s":26,"e":0},{"t":"لَنَحۡنُ","k":"26:44","s":26,"e":0}]},{"n":5,"type":"ayah","words":[{"t":"ٱلۡغَٰلِبُونَ","k":"26:44","s":26,"e":0},{"t":"٤٤","k":"26:44","s":26,"e":1},{"t":"فَأَلۡقَىٰ","k":"26:45","s":26,"e":0},{"t":"مُوسَىٰ","k":"26:45","s":26,"e":0},{"t":"عَصَاهُ","k":"26:45","s":26,"e":0},{"t":"فَإِذَا","k":"26:45","s":26,"e":0},{"t":"هِيَ","k":"26:45","s":26,"e":0},{"t":"تَلۡقَفُ","k":"26:45","s":26,"e":0},{"t":"مَا","k":"26:45","s":26,"e":0},{"t":"يَأۡفِكُونَ","k":"26:45","s":26,"e":0}]},{"n":6,"type":"ayah","words":[{"t":"٤٥","k":"26:45","s":26,"e":1},{"t":"فَأُلۡقِيَ","k":"26:46","s":26,"e":0},{"t":"ٱلسَّحَرَةُ","k":"26:46","s":26,"e":0},{"t":"سَٰجِدِينَ","k":"26:46","s":26,"e":0},{"t":"٤٦","k":"26:46","s":26,"e":1},{"t":"قَالُوٓاْ","k":"26:47","s":26,"e":0},{"t":"ءَامَنَّا","k":"26:47","s":26,"e":0},{"t":"بِرَبِّ","k":"26:47","s":26,"e":0},{"t":"ٱلۡعَٰلَمِينَ","k":"26:47","s":26,"e":0},{"t":"٤٧","k":"26:47","s":26,"e":1}]},{"n":7,"type":"ayah","words":[{"t":"رَبِّ","k":"26:48","s":26,"e":0},{"t":"مُوسَىٰ","k":"26:48","s":26,"e":0},{"t":"وَهَٰرُونَ","k":"26:48","s":26,"e":0},{"t":"٤٨","k":"26:48","s":26,"e":1},{"t":"قَالَ","k":"26:49","s":26,"e":0},{"t":"ءَامَنتُمۡ","k":"26:49","s":26,"e":0},{"t":"لَهُۥ","k":"26:49","s":26,"e":0},{"t":"قَبۡلَ","k":"26:49","s":26,"e":0},{"t":"أَنۡ","k":"26:49","s":26,"e":0},{"t":"ءَاذَنَ","k":"26:49","s":26,"e":0},{"t":"لَكُمۡۖ","k":"26:49","s":26,"e":0},{"t":"إِنَّهُۥ","k":"26:49","s":26,"e":0}]},{"n":8,"type":"ayah","words":[{"t":"لَكَبِيرُكُمُ","k":"26:49","s":26,"e":0},{"t":"ٱلَّذِي","k":"26:49","s":26,"e":0},{"t":"عَلَّمَكُمُ","k":"26:49","s":26,"e":0},{"t":"ٱلسِّحۡرَ","k":"26:49","s":26,"e":0},{"t":"فَلَسَوۡفَ","k":"26:49","s":26,"e":0},{"t":"تَعۡلَمُونَۚ","k":"26:49","s":26,"e":0},{"t":"لَأُقَطِّعَنَّ","k":"26:49","s":26,"e":0},{"t":"أَيۡدِيَكُمۡ","k":"26:49","s":26,"e":0}]},{"n":9,"type":"ayah","words":[{"t":"وَأَرۡجُلَكُم","k":"26:49","s":26,"e":0},{"t":"مِّنۡ","k":"26:49","s":26,"e":0},{"t":"خِلَٰفٖ","k":"26:49","s":26,"e":0},{"t":"وَلَأُصَلِّبَنَّكُمۡ","k":"26:49","s":26,"e":0},{"t":"أَجۡمَعِينَ","k":"26:49","s":26,"e":0},{"t":"٤٩","k":"26:49","s":26,"e":1},{"t":"قَالُواْ","k":"26:50","s":26,"e":0},{"t":"لَا","k":"26:50","s":26,"e":0},{"t":"ضَيۡرَۖ","k":"26:50","s":26,"e":0},{"t":"إِنَّآ","k":"26:50","s":26,"e":0}]},{"n":10,"type":"ayah","words":[{"t":"إِلَىٰ","k":"26:50","s":26,"e":0},{"t":"رَبِّنَا","k":"26:50","s":26,"e":0},{"t":"مُنقَلِبُونَ","k":"26:50","s":26,"e":0},{"t":"٥٠","k":"26:50","s":26,"e":1},{"t":"إِنَّا","k":"26:51","s":26,"e":0},{"t":"نَطۡمَعُ","k":"26:51","s":26,"e":0},{"t":"أَن","k":"26:51","s":26,"e":0},{"t":"يَغۡفِرَ","k":"26:51","s":26,"e":0},{"t":"لَنَا","k":"26:51","s":26,"e":0},{"t":"رَبُّنَا","k":"26:51","s":26,"e":0},{"t":"خَطَٰيَٰنَآ","k":"26:51","s":26,"e":0},{"t":"أَن","k":"26:51","s":26,"e":0},{"t":"كُنَّآ","k":"26:51","s":26,"e":0}]},{"n":11,"type":"ayah","words":[{"t":"أَوَّلَ","k":"26:51","s":26,"e":0},{"t":"ٱلۡمُؤۡمِنِينَ","k":"26:51","s":26,"e":0},{"t":"٥١","k":"26:51","s":26,"e":1},{"t":"۞ وَأَوۡحَيۡنَآ","k":"26:52","s":26,"e":0},{"t":"إِلَىٰ","k":"26:52","s":26,"e":0},{"t":"مُوسَىٰٓ","k":"26:52","s":26,"e":0},{"t":"أَنۡ","k":"26:52","s":26,"e":0},{"t":"أَسۡرِ","k":"26:52","s":26,"e":0},{"t":"بِعِبَادِيٓ","k":"26:52","s":26,"e":0},{"t":"إِنَّكُم","k":"26:52","s":26,"e":0}]},{"n":12,"type":"ayah","words":[{"t":"مُّتَّبَعُونَ","k":"26:52","s":26,"e":0},{"t":"٥٢","k":"26:52","s":26,"e":1},{"t":"فَأَرۡسَلَ","k":"26:53","s":26,"e":0},{"t":"فِرۡعَوۡنُ","k":"26:53","s":26,"e":0},{"t":"فِي","k":"26:53","s":26,"e":0},{"t":"ٱلۡمَدَآئِنِ","k":"26:53","s":26,"e":0},{"t":"حَٰشِرِينَ","k":"26:53","s":26,"e":0},{"t":"٥٣","k":"26:53","s":26,"e":1},{"t":"إِنَّ","k":"26:54","s":26,"e":0},{"t":"هَٰٓؤُلَآءِ","k":"26:54","s":26,"e":0}]},{"n":13,"type":"ayah","words":[{"t":"لَشِرۡذِمَةٞ","k":"26:54","s":26,"e":0},{"t":"قَلِيلُونَ","k":"26:54","s":26,"e":0},{"t":"٥٤","k":"26:54","s":26,"e":1},{"t":"وَإِنَّهُمۡ","k":"26:55","s":26,"e":0},{"t":"لَنَا","k":"26:55","s":26,"e":0},{"t":"لَغَآئِظُونَ","k":"26:55","s":26,"e":0},{"t":"٥٥","k":"26:55","s":26,"e":1},{"t":"وَإِنَّا","k":"26:56","s":26,"e":0},{"t":"لَجَمِيعٌ","k":"26:56","s":26,"e":0},{"t":"حَٰذِرُونَ","k":"26:56","s":26,"e":0}]},{"n":14,"type":"ayah","words":[{"t":"٥٦","k":"26:56","s":26,"e":1},{"t":"فَأَخۡرَجۡنَٰهُم","k":"26:57","s":26,"e":0},{"t":"مِّن","k":"26:57","s":26,"e":0},{"t":"جَنَّٰتٖ","k":"26:57","s":26,"e":0},{"t":"وَعُيُونٖ","k":"26:57","s":26,"e":0},{"t":"٥٧","k":"26:57","s":26,"e":1},{"t":"وَكُنُوزٖ","k":"26:58","s":26,"e":0},{"t":"وَمَقَامٖ","k":"26:58","s":26,"e":0},{"t":"كَرِيمٖ","k":"26:58","s":26,"e":0},{"t":"٥٨","k":"26:58","s":26,"e":1}]},{"n":15,"type":"ayah","words":[{"t":"كَذَٰلِكَۖ","k":"26:59","s":26,"e":0},{"t":"وَأَوۡرَثۡنَٰهَا","k":"26:59","s":26,"e":0},{"t":"بَنِيٓ","k":"26:59","s":26,"e":0},{"t":"إِسۡرَٰٓءِيلَ","k":"26:59","s":26,"e":0},{"t":"٥٩","k":"26:59","s":26,"e":1},{"t":"فَأَتۡبَعُوهُم","k":"26:60","s":26,"e":0},{"t":"مُّشۡرِقِينَ","k":"26:60","s":26,"e":0},{"t":"٦٠","k":"26:60","s":26,"e":1}]}]}