{"page":541,"lines":[{"n":1,"type":"ayah","words":[{"t":"لَقَدۡ","k":"57:25","s":57,"e":0},{"t":"أَرۡسَلۡنَا","k":"57:25","s":57,"e":0},{"t":"رُسُلَنَا","k":"57:25","s":57,"e":0},{"t":"بِٱلۡبَيِّنَٰتِ","k":"57:25","s":57,"e":0},{"t":"وَأَنزَلۡنَا","k":"57:25","s":57,"e":0},{"t":"مَعَهُمُ","k":"57:25","s":57,"e":0},{"t":"ٱلۡكِتَٰبَ","k":"57:25","s":57,"e":0}]},{"n":2,"type":"ayah","words":[{"t":"وَٱلۡمِيزَانَ","k":"57:25","s":57,"e":0},{"t":"لِيَقُومَ","k":"57:25","s":57,"e":0},{"t":"ٱلنَّاسُ","k":"57:25","s":57,"e":0},{"t":"بِٱلۡقِسۡطِۖ","k":"57:25","s":57,"e":0},{"t":"وَأَنزَلۡنَا","k":"57:25","s":57,"e":0},{"t":"ٱلۡحَدِيدَ","k":"57:25","s":57,"e":0},{"t":"فِيهِ","k":"57:25","s":57,"e":0}]},{"n":3,"type":"ayah","words":[{"t":"بَأۡسٞ","k":"57:25","s":57,"e":0},{"t":"شَدِيدٞ","k":"57:25","s":57,"e":0},{"t":"وَمَنَٰفِعُ","k":"57:25","s":57,"e":0},{"t":"لِلنَّاسِ","k":"57:25","s":57,"e":0},{"t":"وَلِيَعۡلَمَ","k":"57:25","s":57,"e":0},{"t":"ٱللَّهُ","k":"57:25","s":57,"e":0},{"t":"مَن","k":"57:25","s":57,"e":0},{"t":"يَنصُرُهُۥ","k":"57:25","s":57,"e":0},{"t":"وَرُسُلَهُۥ","k":"57:25","s":57,"e":0}]},{"n":4,"type":"ayah","words":[{"t":"بِٱلۡغَيۡبِۚ","k":"57:25","s":57,"e":0},{"t":"إِنَّ","k":"57:25","s":57,"e":0},{"t":"ٱللَّهَ","k":"57:25","s":57,"e":0},{"t":"قَوِيٌّ","k":"57:25","s":57,"e":0},{"t":"عَزِيزٞ","k":"57:25","s":57,"e":0},{"t":"٢٥","k":"57:25","s":57,"e":1},{"t":"وَلَقَدۡ","k":"57:26","s":57,"e":0},{"t":"أَرۡسَلۡنَا","k":"57:26","s":57,"e":0},{"t":"نُوحٗا","k":"57:26","s":57,"e":0},{"t":"وَإِبۡرَٰهِيمَ","k":"57:26","s":57,"e":0}]},{"n":5,"type":"ayah","words":[{"t":"وَجَعَلۡنَا","k":"57:26","s":57,"e":0},{"t":"فِي","k":"57:26","s":57,"e":0},{"t":"ذُرِّيَّتِهِمَا","k":"57:26","s":57,"e":0},{"t":"ٱلنُّبُوَّةَ","k":"57:26","s":57,"e":0},{"t":"وَٱلۡكِتَٰبَۖ","k":"57:26","s":57,"e":0},{"t":"فَمِنۡهُم","k":"57:26","s":57,"e":0},{"t":"مُّهۡتَدٖۖ","k":"57:26","s":57,"e":0}]},{"n":6,"type":"ayah","words":[{"t":"وَكَثِيرٞ","k":"57:26","s":57,"e":0},{"t":"مِّنۡهُمۡ","k":"57:26","s":57,"e":0},{"t":"فَٰسِقُونَ","k":"57:26","s":57,"e":0},{"t":"٢٦","k":"57:26","s":57,"e":1},{"t":"ثُمَّ","k":"57:27","s":57,"e":0},{"t":"قَفَّيۡنَا","k":"57:27","s":57,"e":0},{"t":"عَلَىٰٓ","k":"57:27","s":57,"e":0},{"t":"ءَاثَٰرِهِم","k":"57:27","s":57,"e":0}]},{"n":7,"type":"ayah","words":[{"t":"بِرُسُلِنَا","k":"57:27","s":57,"e":0},{"t":"وَقَفَّيۡنَا","k":"57:27","s":57,"e":0},{"t":"بِعِيسَى","k":"57:27","s":57,"e":0},{"t":"ٱبۡنِ","k":"57:27","s":57,"e":0},{"t":"مَرۡيَمَ","k":"57:27","s":57,"e":0},{"t":"وَءَاتَيۡنَٰهُ","k":"57:27","s":57,"e":0},{"t":"ٱلۡإِنجِيلَۖ","k":"57:27","s":57,"e":0}]},{"n":8,"type":"ayah","words":[{"t":"وَجَعَلۡنَا","k":"57:27","s":57,"e":0},{"t":"فِي","k":"57:27","s":57,"e":0},{"t":"قُلُوبِ","k":"57:27","s":57,"e":0},{"t":"ٱلَّذِينَ","k":"57:27","s":57,"e":0},{"t":"ٱتَّبَعُوهُ","k":"57:27","s":57,"e":0},{"t":"رَأۡفَةٗ","k":"57:27","s":57,"e":0},{"t":"وَرَحۡمَةٗۚ","k":"57:27","s":57,"e":0},{"t":"وَرَهۡبَانِيَّةً","k":"57:27","s":57,"e":0}]},{"n":9,"type":"ayah","words":[{"t":"ٱبۡتَدَعُوهَا","k":"57:27","s":57,"e":0},{"t":"مَا","k":"57:27","s":57,"e":0},{"t":"كَتَبۡنَٰهَا","k":"57:27","s":57,"e":0},{"t":"عَلَيۡهِمۡ","k":"57:27","s":57,"e":0},{"t":"إِلَّا","k":"57:27","s":57,"e":0},{"t":"ٱبۡتِغَآءَ","k":"57:27","s":57,"e":0},{"t":"رِضۡوَٰنِ","k":"57:27","s":57,"e":0},{"t":"ٱللَّهِ","k":"57:27","s":57,"e":0},{"t":"فَمَا","k":"57:27","s":57,"e":0}]},{"n":10,"type":"ayah","words":[{"t":"رَعَوۡهَا","k":"57:27","s":57,"e":0},{"t":"حَقَّ","k":"57:27","s":57,"e":0},{"t":"رِعَايَتِهَاۖ","k":"57:27","s":57,"e":0},{"t":"فَـَٔاتَيۡنَا","k":"57:27","s":57,"e":0},{"t":"ٱلَّذِينَ","k":"57:27","s":57,"e":0},{"t":"ءَامَنُواْ","k":"57:27","s":57,"e":0},{"t":"مِنۡهُمۡ","k":"57:27","s":57,"e":0},{"t":"أَجۡرَهُمۡۖ","k":"57:27","s":57,"e":0}]},{"n":11,"type":"ayah","words":[{"t":"وَكَثِيرٞ","k":"57:27","s":57,"e":0},{"t":"مِّنۡهُمۡ","k":"57:27","s":57,"e":0},{"t":"فَٰسِقُونَ","k":"57:27","s":57,"e":0},{"t":"٢٧","k":"57:27","s":57,"e":1},{"t":"يَٰٓأَيُّهَا","k":"57:28","s":57,"e":0},{"t":"ٱلَّذِينَ","k":"57:28","s":57,"e":0},{"t":"ءَامَنُواْ","k":"57:28","s":57,"e":0},{"t":"ٱتَّقُواْ","k":"57:28","s":57,"e":0},{"t":"ٱللَّهَ","k":"57:28","s":57,"e":0}]},{"n":12,"type":"ayah","words":[{"t":"وَءَامِنُواْ","k":"57:28","s":57,"e":0},{"t":"بِرَسُولِهِۦ","k":"57:28","s":57,"e":0},{"t":"يُؤۡتِكُمۡ","k":"57:28","s":57,"e":0},{"t":"كِفۡلَيۡنِ","k":"57:28","s":57,"e":0},{"t":"مِن","k":"57:28","s":57,"e":0},{"t":"رَّحۡمَتِهِۦ","k":"57:28","s":57,"e":0},{"t":"وَيَجۡعَل","k":"57:28","s":57,"e":0},{"t":"لَّكُمۡ","k":"57:28","s":57,"e":0}]},{"n":13,"type":"ayah","words":[{"t":"نُورٗا","k":"57:28","s":57,"e":0},{"t":"تَمۡشُونَ","k":"57:28","s":57,"e":0},{"t":"بِهِۦ","k":"57:28","s":57,"e":0},{"t":"وَيَغۡفِرۡ","k":"57:28","s":57,"e":0},{"t":"لَكُمۡۚ","k":"57:28","s":57,"e":0},{"t":"وَٱللَّهُ","k":"57:28","s":57,"e":0},{"t":"غَفُورٞ","k":"57:28","s":57,"e":0},{"t":"رَّحِيمٞ","k":"57:28","s":57,"e":0},{"t":"٢٨","k":"57:28","s":57,"e":1},{"t":"لِّئَلَّا","k":"57:29","s":57,"e":0},{"t":"يَعۡلَمَ","k":"57:29","s":57,"e":0}]},{"n":14,"type":"ayah","words":[{"t":"أَهۡلُ","k":"57:29","s":57,"e":0},{"t":"ٱلۡكِتَٰبِ","k":"57:29","s":57,"e":0},{"t":"أَلَّا","k":"57:29","s":57,"e":0},{"t":"يَقۡدِرُونَ","k":"57:29","s":57,"e":0},{"t":"عَلَىٰ","k":"57:29","s":57,"e":0},{"t":"شَيۡءٖ","k":"57:29","s":57,"e":0},{"t":"مِّن","k":"57:29","s":57,"e":0},{"t":"فَضۡلِ","k":"57:29","s":57,"e":0},{"t":"ٱللَّهِ","k":"57:29","s":57,"e":0},{"t":"وَأَنَّ","k":"57:29","s":57,"e":0}]},{"n":15,"type":"ayah","words":[{"t":"ٱلۡفَضۡلَ","k":"57:29","s":57,"e":0},{"t":"بِيَدِ","k":"57:29","s":57,"e":0},{"t":"ٱللَّهِ","k":"57:29","s":57,"e":0},{"t":"يُؤۡتِيهِ","k":"57:29","s":57,"e":0},{"t":"مَن","k":"57:29","s":57,"e":0},{"t":"يَشَآءُۚ","k":"57:29","s":57,"e":0},{"t":"وَٱللَّهُ","k":"57:29","s":57,"e":0},{"t":"ذُو","k":"57:29","s":57,"e":0},{"t":"ٱلۡفَضۡلِ","k":"57:29","s":57,"e":0},{"t":"ٱلۡعَظِيمِ","k":"57:29","s":57,"e":0},{"t":"٢٩","k":"57:29","s":57,"e":1}],"c":1}]}