{"page":45,"lines":[{"n":1,"type":"ayah","words":[{"t":"وَمَثَلُ","k":"2:265","s":2,"e":0},{"t":"ٱلَّذِينَ","k":"2:265","s":2,"e":0},{"t":"يُنفِقُونَ","k":"2:265","s":2,"e":0},{"t":"أَمۡوَٰلَهُمُ","k":"2:265","s":2,"e":0},{"t":"ٱبۡتِغَآءَ","k":"2:265","s":2,"e":0},{"t":"مَرۡضَاتِ","k":"2:265","s":2,"e":0},{"t":"ٱللَّهِ","k":"2:265","s":2,"e":0}]},{"n":2,"type":"ayah","words":[{"t":"وَتَثۡبِيتٗا","k":"2:265","s":2,"e":0},{"t":"مِّنۡ","k":"2:265","s":2,"e":0},{"t":"أَنفُسِهِمۡ","k":"2:265","s":2,"e":0},{"t":"كَمَثَلِ","k":"2:265","s":2,"e":0},{"t":"جَنَّةِۭ","k":"2:265","s":2,"e":0},{"t":"بِرَبۡوَةٍ","k":"2:265","s":2,"e":0},{"t":"أَصَابَهَا","k":"2:265","s":2,"e":0},{"t":"وَابِلٞ","k":"2:265","s":2,"e":0}]},{"n":3,"type":"ayah","words":[{"t":"فَـَٔاتَتۡ","k":"2:265","s":2,"e":0},{"t":"أُكُلَهَا","k":"2:265","s":2,"e":0},{"t":"ضِعۡفَيۡنِ","k":"2:265","s":2,"e":0},{"t":"فَإِن","k":"2:265","s":2,"e":0},{"t":"لَّمۡ","k":"2:265","s":2,"e":0},{"t":"يُصِبۡهَا","k":"2:265","s":2,"e":0},{"t":"وَابِلٞ","k":"2:265","s":2,"e":0},{"t":"فَطَلّٞۗ","k":"2:265","s":2,"e":0}]},{"n":4,"type":"ayah","words":[{"t":"وَٱللَّهُ","k":"2:265","s":2,"e":0},{"t":"بِمَا","k":"2:265","s":2,"e":0},{"t":"تَعۡمَلُونَ","k":"2:265","s":2,"e":0},{"t":"بَصِيرٌ","k":"2:265","s":2,"e":0},{"t":"٢٦٥","k":"2:265","s":2,"e":1},{"t":"أَيَوَدُّ","k":"2:266","s":2,"e":0},{"t":"أَحَدُكُمۡ","k":"2:266","s":2,"e":0},{"t":"أَن","k":"2:266","s":2,"e":0},{"t":"تَكُونَ","k":"2:266","s":2,"e":0}]},{"n":5,"type":"ayah","words":[{"t":"لَهُۥ","k":"2:266","s":2,"e":0},{"t":"جَنَّةٞ","k":"2:266","s":2,"e":0},{"t":"مِّن","k":"2:266","s":2,"e":0},{"t":"نَّخِيلٖ","k":"2:266","s":2,"e":0},{"t":"وَأَعۡنَابٖ","k":"2:266","s":2,"e":0},{"t":"تَجۡرِي","k":"2:266","s":2,"e":0},{"t":"مِن","k":"2:266","s":2,"e":0},{"t":"تَحۡتِهَا","k":"2:266","s":2,"e":0},{"t":"ٱلۡأَنۡهَٰرُ","k":"2:266","s":2,"e":0},{"t":"لَهُۥ","k":"2:266","s":2,"e":0}]},{"n":6,"type":"ayah","words":[{"t":"فِيهَا","k":"2:266","s":2,"e":0},{"t":"مِن","k":"2:266","s":2,"e":0},{"t":"كُلِّ","k":"2:266","s":2,"e":0},{"t":"ٱلثَّمَرَٰتِ","k":"2:266","s":2,"e":0},{"t":"وَأَصَابَهُ","k":"2:266","s":2,"e":0},{"t":"ٱلۡكِبَرُ","k":"2:266","s":2,"e":0},{"t":"وَلَهُۥ","k":"2:266","s":2,"e":0},{"t":"ذُرِّيَّةٞ","k":"2:266","s":2,"e":0},{"t":"ضُعَفَآءُ","k":"2:266","s":2,"e":0}]},{"n":7,"type":"ayah","words":[{"t":"فَأَصَابَهَآ","k":"2:266","s":2,"e":0},{"t":"إِعۡصَارٞ","k":"2:266","s":2,"e":0},{"t":"فِيهِ","k":"2:266","s":2,"e":0},{"t":"نَارٞ","k":"2:266","s":2,"e":0},{"t":"فَٱحۡتَرَقَتۡۗ","k":"2:266","s":2,"e":0},{"t":"كَذَٰلِكَ","k":"2:266","s":2,"e":0},{"t":"يُبَيِّنُ","k":"2:266","s":2,"e":0},{"t":"ٱللَّهُ","k":"2:266","s":2,"e":0}]},{"n":8,"type":"ayah","words":[{"t":"لَكُمُ","k":"2:266","s":2,"e":0},{"t":"ٱلۡأٓيَٰتِ","k":"2:266","s":2,"e":0},{"t":"لَعَلَّكُمۡ","k":"2:266","s":2,"e":0},{"t":"تَتَفَكَّرُونَ","k":"2:266","s":2,"e":0},{"t":"٢٦٦","k":"2:266","s":2,"e":1},{"t":"يَٰٓأَيُّهَا","k":"2:267","s":2,"e":0},{"t":"ٱلَّذِينَ","k":"2:267","s":2,"e":0}]},{"n":9,"type":"ayah","words":[{"t":"ءَامَنُوٓاْ","k":"2:267","s":2,"e":0},{"t":"أَنفِقُواْ","k":"2:267","s":2,"e":0},{"t":"مِن","k":"2:267","s":2,"e":0},{"t":"طَيِّبَٰتِ","k":"2:267","s":2,"e":0},{"t":"مَا","k":"2:267","s":2,"e":0},{"t":"كَسَبۡتُمۡ","k":"2:267","s":2,"e":0},{"t":"وَمِمَّآ","k":"2:267","s":2,"e":0},{"t":"أَخۡرَجۡنَا","k":"2:267","s":2,"e":0}]},{"n":10,"type":"ayah","words":[{"t":"لَكُم","k":"2:267","s":2,"e":0},{"t":"مِّنَ","k":"2:267","s":2,"e":0},{"t":"ٱلۡأَرۡضِۖ","k":"2:267","s":2,"e":0},{"t":"وَلَا","k":"2:267","s":2,"e":0},{"t":"تَيَمَّمُواْ","k":"2:267","s":2,"e":0},{"t":"ٱلۡخَبِيثَ","k":"2:267","s":2,"e":0},{"t":"مِنۡهُ","k":"2:267","s":2,"e":0},{"t":"تُنفِقُونَ","k":"2:267","s":2,"e":0},{"t":"وَلَسۡتُم","k":"2:267","s":2,"e":0}]},{"n":11,"type":"ayah","words":[{"t":"بِـَٔاخِذِيهِ","k":"2:267","s":2,"e":0},{"t":"إِلَّآ","k":"2:267","s":2,"e":0},{"t":"أَن","k":"2:267","s":2,"e":0},{"t":"تُغۡمِضُواْ","k":"2:267","s":2,"e":0},{"t":"فِيهِۚ","k":"2:267","s":2,"e":0},{"t":"وَٱعۡلَمُوٓاْ","k":"2:267","s":2,"e":0},{"t":"أَنَّ","k":"2:267","s":2,"e":0},{"t":"ٱللَّهَ","k":"2:267","s":2,"e":0},{"t":"غَنِيٌّ","k":"2:267","s":2,"e":0},{"t":"حَمِيدٌ","k":"2:267","s":2,"e":0}]},{"n":12,"type":"ayah","words":[{"t":"٢٦٧","k":"2:267","s":2,"e":1},{"t":"ٱلشَّيۡطَٰنُ","k":"2:268","s":2,"e":0},{"t":"يَعِدُكُمُ","k":"2:268","s":2,"e":0},{"t":"ٱلۡفَقۡرَ","k":"2:268","s":2,"e":0},{"t":"وَيَأۡمُرُكُم","k":"2:268","s":2,"e":0},{"t":"بِٱلۡفَحۡشَآءِۖ","k":"2:268","s":2,"e":0}]},{"n":13,"type":"ayah","words":[{"t":"وَٱللَّهُ","k":"2:268","s":2,"e":0},{"t":"يَعِدُكُم","k":"2:268","s":2,"e":0},{"t":"مَّغۡفِرَةٗ","k":"2:268","s":2,"e":0},{"t":"مِّنۡهُ","k":"2:268","s":2,"e":0},{"t":"وَفَضۡلٗاۗ","k":"2:268","s":2,"e":0},{"t":"وَٱللَّهُ","k":"2:268","s":2,"e":0},{"t":"وَٰسِعٌ","k":"2:268","s":2,"e":0},{"t":"عَلِيمٞ","k":"2:268","s":2,"e":0},{"t":"٢٦٨","k":"2:268","s":2,"e":1}]},{"n":14,"type":"ayah","words":[{"t":"يُؤۡتِي","k":"2:269","s":2,"e":0},{"t":"ٱلۡحِكۡمَةَ","k":"2:269","s":2,"e":0},{"t":"مَن","k":"2:269","s":2,"e":0},{"t":"يَشَآءُۚ","k":"2:269","s":2,"e":0},{"t":"وَمَن","k":"2:269","s":2,"e":0},{"t":"يُؤۡتَ","k":"2:269","s":2,"e":0},{"t":"ٱلۡحِكۡمَةَ","k":"2:269","s":2,"e":0},{"t":"فَقَدۡ","k":"2:269","s":2,"e":0}]},{"n":15,"type":"ayah","words":[{"t":"أُوتِيَ","k":"2:269","s":2,"e":0},{"t":"خَيۡرٗا","k":"2:269","s":2,"e":0},{"t":"كَثِيرٗاۗ","k":"2:269","s":2,"e":0},{"t":"وَمَا","k":"2:269","s":2,"e":0},{"t":"يَذَّكَّرُ","k":"2:269","s":2,"e":0},{"t":"إِلَّآ","k":"2:269","s":2,"e":0},{"t":"أُوْلُواْ","k":"2:269","s":2,"e":0},{"t":"ٱلۡأَلۡبَٰبِ","k":"2:269","s":2,"e":0},{"t":"٢٦٩","k":"2:269","s":2,"e":1}]}]}