{"page":308,"lines":[{"n":1,"type":"ayah","words":[{"t":"وَأَنذِرۡهُمۡ","k":"19:39","s":19,"e":0},{"t":"يَوۡمَ","k":"19:39","s":19,"e":0},{"t":"ٱلۡحَسۡرَةِ","k":"19:39","s":19,"e":0},{"t":"إِذۡ","k":"19:39","s":19,"e":0},{"t":"قُضِيَ","k":"19:39","s":19,"e":0},{"t":"ٱلۡأَمۡرُ","k":"19:39","s":19,"e":0},{"t":"وَهُمۡ","k":"19:39","s":19,"e":0},{"t":"فِي","k":"19:39","s":19,"e":0},{"t":"غَفۡلَةٖ","k":"19:39","s":19,"e":0},{"t":"وَهُمۡ","k":"19:39","s":19,"e":0},{"t":"لَا","k":"19:39","s":19,"e":0},{"t":"يُؤۡمِنُونَ","k":"19:39","s":19,"e":0}]},{"n":2,"type":"ayah","words":[{"t":"٣٩","k":"19:39","s":19,"e":1},{"t":"إِنَّا","k":"19:40","s":19,"e":0},{"t":"نَحۡنُ","k":"19:40","s":19,"e":0},{"t":"نَرِثُ","k":"19:40","s":19,"e":0},{"t":"ٱلۡأَرۡضَ","k":"19:40","s":19,"e":0},{"t":"وَمَنۡ","k":"19:40","s":19,"e":0},{"t":"عَلَيۡهَا","k":"19:40","s":19,"e":0},{"t":"وَإِلَيۡنَا","k":"19:40","s":19,"e":0},{"t":"يُرۡجَعُونَ","k":"19:40","s":19,"e":0},{"t":"٤٠","k":"19:40","s":19,"e":1},{"t":"وَٱذۡكُرۡ","k":"19:41","s":19,"e":0}]},{"n":3,"type":"ayah","words":[{"t":"فِي","k":"19:41","s":19,"e":0},{"t":"ٱلۡكِتَٰبِ","k":"19:41","s":19,"e":0},{"t":"إِبۡرَٰهِيمَۚ","k":"19:41","s":19,"e":0},{"t":"إِنَّهُۥ","k":"19:41","s":19,"e":0},{"t":"كَانَ","k":"19:41","s":19,"e":0},{"t":"صِدِّيقٗا","k":"19:41","s":19,"e":0},{"t":"نَّبِيًّا","k":"19:41","s":19,"e":0},{"t":"٤١","k":"19:41","s":19,"e":1},{"t":"إِذۡ","k":"19:42","s":19,"e":0},{"t":"قَالَ","k":"19:42","s":19,"e":0},{"t":"لِأَبِيهِ","k":"19:42","s":19,"e":0},{"t":"يَٰٓأَبَتِ","k":"19:42","s":19,"e":0}]},{"n":4,"type":"ayah","words":[{"t":"لِمَ","k":"19:42","s":19,"e":0},{"t":"تَعۡبُدُ","k":"19:42","s":19,"e":0},{"t":"مَا","k":"19:42","s":19,"e":0},{"t":"لَا","k":"19:42","s":19,"e":0},{"t":"يَسۡمَعُ","k":"19:42","s":19,"e":0},{"t":"وَلَا","k":"19:42","s":19,"e":0},{"t":"يُبۡصِرُ","k":"19:42","s":19,"e":0},{"t":"وَلَا","k":"19:42","s":19,"e":0},{"t":"يُغۡنِي","k":"19:42","s":19,"e":0},{"t":"عَنكَ","k":"19:42","s":19,"e":0},{"t":"شَيۡـٔٗا","k":"19:42","s":19,"e":0},{"t":"٤٢","k":"19:42","s":19,"e":1},{"t":"يَٰٓأَبَتِ","k":"19:43","s":19,"e":0}]},{"n":5,"type":"ayah","words":[{"t":"إِنِّي","k":"19:43","s":19,"e":0},{"t":"قَدۡ","k":"19:43","s":19,"e":0},{"t":"جَآءَنِي","k":"19:43","s":19,"e":0},{"t":"مِنَ","k":"19:43","s":19,"e":0},{"t":"ٱلۡعِلۡمِ","k":"19:43","s":19,"e":0},{"t":"مَا","k":"19:43","s":19,"e":0},{"t":"لَمۡ","k":"19:43","s":19,"e":0},{"t":"يَأۡتِكَ","k":"19:43","s":19,"e":0},{"t":"فَٱتَّبِعۡنِيٓ","k":"19:43","s":19,"e":0},{"t":"أَهۡدِكَ","k":"19:43","s":19,"e":0},{"t":"صِرَٰطٗا","k":"19:43","s":19,"e":0}]},{"n":6,"type":"ayah","words":[{"t":"سَوِيّٗا","k":"19:43","s":19,"e":0},{"t":"٤٣","k":"19:43","s":19,"e":1},{"t":"يَٰٓأَبَتِ","k":"19:44","s":19,"e":0},{"t":"لَا","k":"19:44","s":19,"e":0},{"t":"تَعۡبُدِ","k":"19:44","s":19,"e":0},{"t":"ٱلشَّيۡطَٰنَۖ","k":"19:44","s":19,"e":0},{"t":"إِنَّ","k":"19:44","s":19,"e":0},{"t":"ٱلشَّيۡطَٰنَ","k":"19:44","s":19,"e":0},{"t":"كَانَ","k":"19:44","s":19,"e":0},{"t":"لِلرَّحۡمَٰنِ","k":"19:44","s":19,"e":0}]},{"n":7,"type":"ayah","words":[{"t":"عَصِيّٗا","k":"19:44","s":19,"e":0},{"t":"٤٤","k":"19:44","s":19,"e":1},{"t":"يَٰٓأَبَتِ","k":"19:45","s":19,"e":0},{"t":"إِنِّيٓ","k":"19:45","s":19,"e":0},{"t":"أَخَافُ","k":"19:45","s":19,"e":0},{"t":"أَن","k":"19:45","s":19,"e":0},{"t":"يَمَسَّكَ","k":"19:45","s":19,"e":0},{"t":"عَذَابٞ","k":"19:45","s":19,"e":0},{"t":"مِّنَ","k":"19:45","s":19,"e":0},{"t":"ٱلرَّحۡمَٰنِ","k":"19:45","s":19,"e":0}]},{"n":8,"type":"ayah","words":[{"t":"فَتَكُونَ","k":"19:45","s":19,"e":0},{"t":"لِلشَّيۡطَٰنِ","k":"19:45","s":19,"e":0},{"t":"وَلِيّٗا","k":"19:45","s":19,"e":0},{"t":"٤٥","k":"19:45","s":19,"e":1},{"t":"قَالَ","k":"19:46","s":19,"e":0},{"t":"أَرَاغِبٌ","k":"19:46","s":19,"e":0},{"t":"أَنتَ","k":"19:46","s":19,"e":0},{"t":"عَنۡ","k":"19:46","s":19,"e":0},{"t":"ءَالِهَتِي","k":"19:46","s":19,"e":0}]},{"n":9,"type":"ayah","words":[{"t":"يَٰٓإِبۡرَٰهِيمُۖ","k":"19:46","s":19,"e":0},{"t":"لَئِن","k":"19:46","s":19,"e":0},{"t":"لَّمۡ","k":"19:46","s":19,"e":0},{"t":"تَنتَهِ","k":"19:46","s":19,"e":0},{"t":"لَأَرۡجُمَنَّكَۖ","k":"19:46","s":19,"e":0},{"t":"وَٱهۡجُرۡنِي","k":"19:46","s":19,"e":0},{"t":"مَلِيّٗا","k":"19:46","s":19,"e":0},{"t":"٤٦","k":"19:46","s":19,"e":1},{"t":"قَالَ","k":"19:47","s":19,"e":0}]},{"n":10,"type":"ayah","words":[{"t":"سَلَٰمٌ","k":"19:47","s":19,"e":0},{"t":"عَلَيۡكَۖ","k":"19:47","s":19,"e":0},{"t":"سَأَسۡتَغۡفِرُ","k":"19:47","s":19,"e":0},{"t":"لَكَ","k":"19:47","s":19,"e":0},{"t":"رَبِّيٓۖ","k":"19:47","s":19,"e":0},{"t":"إِنَّهُۥ","k":"19:47","s":19,"e":0},{"t":"كَانَ","k":"19:47","s":19,"e":0},{"t":"بِي","k":"19:47","s":19,"e":0},{"t":"حَفِيّٗا","k":"19:47","s":19,"e":0},{"t":"٤٧","k":"19:47","s":19,"e":1}]},{"n":11,"type":"ayah","words":[{"t":"وَأَعۡتَزِلُكُمۡ","k":"19:48","s":19,"e":0},{"t":"وَمَا","k":"19:48","s":19,"e":0},{"t":"تَدۡعُونَ","k":"19:48","s":19,"e":0},{"t":"مِن","k":"19:48","s":19,"e":0},{"t":"دُونِ","k":"19:48","s":19,"e":0},{"t":"ٱللَّهِ","k":"19:48","s":19,"e":0},{"t":"وَأَدۡعُواْ","k":"19:48","s":19,"e":0},{"t":"رَبِّي","k":"19:48","s":19,"e":0},{"t":"عَسَىٰٓ","k":"19:48","s":19,"e":0}]},{"n":12,"type":"ayah","words":[{"t":"أَلَّآ","k":"19:48","s":19,"e":0},{"t":"أَكُونَ","k":"19:48","s":19,"e":0},{"t":"بِدُعَآءِ","k":"19:48","s":19,"e":0},{"t":"رَبِّي","k":"19:48","s":19,"e":0},{"t":"شَقِيّٗا","k":"19:48","s":19,"e":0},{"t":"٤٨","k":"19:48","s":19,"e":1},{"t":"فَلَمَّا","k":"19:49","s":19,"e":0},{"t":"ٱعۡتَزَلَهُمۡ","k":"19:49","s":19,"e":0},{"t":"وَمَا","k":"19:49","s":19,"e":0},{"t":"يَعۡبُدُونَ","k":"19:49","s":19,"e":0}]},{"n":13,"type":"ayah","words":[{"t":"مِن","k":"19:49","s":19,"e":0},{"t":"دُونِ","k":"19:49","s":19,"e":0},{"t":"ٱللَّهِ","k":"19:49","s":19,"e":0},{"t":"وَهَبۡنَا","k":"19:49","s":19,"e":0},{"t":"لَهُۥٓ","k":"19:49","s":19,"e":0},{"t":"إِسۡحَٰقَ","k":"19:49","s":19,"e":0},{"t":"وَيَعۡقُوبَۖ","k":"19:49","s":19,"e":0},{"t":"وَكُلّٗا","k":"19:49","s":19,"e":0},{"t":"جَعَلۡنَا","k":"19:49","s":19,"e":0},{"t":"نَبِيّٗا","k":"19:49","s":19,"e":0},{"t":"٤٩","k":"19:49","s":19,"e":1}]},{"n":14,"type":"ayah","words":[{"t":"وَوَهَبۡنَا","k":"19:50","s":19,"e":0},{"t":"لَهُم","k":"19:50","s":19,"e":0},{"t":"مِّن","k":"19:50","s":19,"e":0},{"t":"رَّحۡمَتِنَا","k":"19:50","s":19,"e":0},{"t":"وَجَعَلۡنَا","k":"19:50","s":19,"e":0},{"t":"لَهُمۡ","k":"19:50","s":19,"e":0},{"t":"لِسَانَ","k":"19:50","s":19,"e":0},{"t":"صِدۡقٍ","k":"19:50","s":19,"e":0},{"t":"عَلِيّٗا","k":"19:50","s":19,"e":0},{"t":"٥٠","k":"19:50","s":19,"e":1}]},{"n":15,"type":"ayah","words":[{"t":"وَٱذۡكُرۡ","k":"19:51","s":19,"e":0},{"t":"فِي","k":"19:51","s":19,"e":0},{"t":"ٱلۡكِتَٰبِ","k":"19:51","s":19,"e":0},{"t":"مُوسَىٰٓۚ","k":"19:51","s":19,"e":0},{"t":"إِنَّهُۥ","k":"19:51","s":19,"e":0},{"t":"كَانَ","k":"19:51","s":19,"e":0},{"t":"مُخۡلَصٗا","k":"19:51","s":19,"e":0},{"t":"وَكَانَ","k":"19:51","s":19,"e":0},{"t":"رَسُولٗا","k":"19:51","s":19,"e":0},{"t":"نَّبِيّٗا","k":"19:51","s":19,"e":0},{"t":"٥١","k":"19:51","s":19,"e":1}]}]}